[{"attr":[{"type":"size","value":"L","id":"EG020101VP0599"},{"type":"size","value":"XL","id":"EG020101VP0699"},{"type":"size","value":"XXL","id":"EG020101VP0799"}],"cat":{"name":"Taager exclusive offers","text":"ุนุฑูุถ ุชุงุฌุฑ ุงูุญุตุฑูุฉ"},"id":"EG020101VP0599","status":"available","desc":"ุนุฑุถ ุงูุตูู ูุงููุตูู ๐ุ ุงูุจุณ ุจุฑุงุญุชู ู ุงุชุดูู ูุน ุนุฑุถ 3 ุชูุดูุฑุช ุตููู Vintage + ุนุฑุถ 3 ุจูุทููู ูููุชูู ุตููู ุ ุฌูุนูุง ูู ุงูุชุฑ ูู ูุทุนู  ุนุดุงู ูููุฑ ูู ู ูุณูู ุนูููุ 6 ูุทุน ูู ุนุฑุถ ูุงุญุฏ ุจุณุนุฑ ููุชุนูุถุด ๐๐","title":"ุนุฑุถ 3 ุชูุดูุฑุช ุตููู Vintage + ุนุฑุถ 3 ุจูุทููู ูููุชูู ุตููู","price":300,"specs":"โข *ุงููููุฒุงุช*\r\nโข - ูููุฒ ุจุฑุณููุงุช ุนุตุฑูุฉ ุนูู ุงูููุถุฉ ุชุฎุทู ุงูุนูู ๐\r\nโข - ุณุฑูุน ู ูุฑูุญ ูุฎุฑูุฌุงุช ุงูุตูู\r\nโข - ุฎุงูุฉ ูููุฒุฉ ุจุชุฏู ุฌุณูู ุงูุณูุงุจูุฉ ุนุงููุฉ\r\nโข - 3 ุชูุดุฑุชุงุช ุจุงููุงู ูุฑุณููุงุช ูุฎุชููุฉ ุชูุฏุฑ ุชูุจุณูู ุจุฃูุชุฑ ูู ุดูู\r\nโข *ุงููุตู*\r\nโข - 3 ุชูุดูุฑุช ุจุฑุณููุงุช ุดุจุงุจู\r\nโข - ุฎุงูุฉ ูุทู ูุฎููุทุฉ ูููุฑุง\r\nโข - ููู ุจูุณู ู ุฑุณูุฉ ุจูุถุงุก ุจุณูุทุฉ ุนูู ุงูุตุฏุฑ\r\nโข - ุงูุฃููุงู ( ุงุณูุฏุ ุงุฎุถุฑุ ุงุตูุฑ )\r\nโข *ุงูููุงุณุงุช*\r\nโข - ููุงุณ : M\r\nโข ููุจุณ ูู 50 : 55 ูููู\r\nโข (ุนุฑุถ 50 ุณูุ ุงูุทูู 64 ุณู)\r\nโข - ููุงุณ : L\r\nโข ููุจุณ ูู 55 : 65 ูููู\r\nโข (ุงูุนุฑุถ 52 ุณูุ ุงูุทูู 66 ุณู)\r\nโข - ููุงุณ : XL\r\nโข ููุจุณ ูู 65 : 70 ูููู\r\nโข (ุงูุนุฑุถ 54 ุณูุ ุงูุทูู 68 ุณู)\r\nโข - ููุงุณ :2XL\r\nโข ููุจุณ ูู 70 : 75 ูููู\r\nโข (ุงูุนุฑุถ 56ุ ุงูุทูู 70 ุณู)\r\nโข *ุงููููุฒุงุช*\r\nโข - ุงุณุชุงูู ูุฑูุญ ู ุนููู\r\nโข - ุฎุงูุฉ ุทุฑูุฉ ูุฑูุญู ูู ุงููุจุณ ููุงุณุจุฉ ููุตูู\r\nโข - ุชุตูููู ุดูู ูุนูู ุงูููุถุฉ ุชูุฏุฑ ุชูุจุณู ูู ุฎุฑูุฌุงุชู ูุน ุตุญุงุจูุ ูู ุงููุงุฏู ู ููุงู ูู ุงูุฌุงูุนุฉ\r\nโข *ุงููุตู*\r\nโข - ุงูุฎุงูุฉ: ุจูุทููู ูููุชูู\r\nโข - ุงูุฃููุงู: (ูุญููุ ุฑูุงุฏูุ ุฃุณูุฏ)\r\nโข *ุงูููุงุณุงุช*\r\nโข ููุงุณ : L (ููุจุณ ูู 55 - 70 ูููู)\r\nโข ููุงุณ : XL (ููุจุณ ูู 70 - 80 ูููู)\r\nโข ููุงุณ :2XL (ููุจุณ ูู 80 - 95 ูููู)\r\nโข","media":["https://tager-uploads.s3.eu-central-1.amazonaws.com/f4d39ef2-d14b-463a-9688-f577d74984ad.jpg","https://tager-uploads.s3.eu-central-1.amazonaws.com/1959b57b-edff-44ca-bc84-40a0ff4c4da9.jpg","https://tager-uploads.s3.eu-central-1.amazonaws.com/1d00b63c-2ff5-4af1-bf40-5ac9eadf73a5.jpg","https://tager-uploads.s3.eu-central-1.amazonaws.com/9cc4d13f-444c-4a04-9c02-a51c921f55b1.jpg","https://tager-uploads.s3.eu-central-1.amazonaws.com/4858a5d6-1841-4dbf-bfdb-fa68197b83b1.jpg","https://tager-uploads.s3.eu-central-1.amazonaws.com/86c2096f-591c-4de7-8f71-cd597993e198.jpg","https://tager-uploads.s3.eu-central-1.amazonaws.com/7a6ff5e4-b9b6-47ff-b0f9-10b8b15641bf.jpg","https://tager-uploads.s3.eu-central-1.amazonaws.com/242a22a4-eda6-41c6-b3a8-60dbb3834b55.jpg"]},{"attr":[{"type":"size","value":"L","id":"EG020101VP0599"},{"type":"size","value":"XL","id":"EG020101VP0699"},{"type":"size","value":"XXL","id":"EG020101VP0799"}],"cat":{"name":"Taager exclusive offers","text":"ุนุฑูุถ ุชุงุฌุฑ ุงูุญุตุฑูุฉ"},"id":"EG020101VP0699","status":"available","desc":"ุนุฑุถ ุงูุตูู ูุงููุตูู ๐ุ ุงูุจุณ ุจุฑุงุญุชู ู ุงุชุดูู ูุน ุนุฑุถ 3 ุชูุดูุฑุช ุตููู Vintage + ุนุฑุถ 3 ุจูุทููู ูููุชูู ุตููู ุ ุฌูุนูุง ูู ุงูุชุฑ ูู ูุทุนู  ุนุดุงู ูููุฑ ูู ู ูุณูู ุนูููุ 6 ูุทุน ูู ุนุฑุถ ูุงุญุฏ ุจุณุนุฑ ููุชุนูุถุด ๐๐","title":"ุนุฑุถ 3 ุชูุดูุฑุช ุตููู Vintage + ุนุฑุถ 3 ุจูุทููู ูููุชูู ุตููู","price":300,"specs":"โข *ุงููููุฒุงุช*\r\nโข - ูููุฒ ุจุฑุณููุงุช ุนุตุฑูุฉ ุนูู ุงูููุถุฉ ุชุฎุทู ุงูุนูู ๐\r\nโข - ุณุฑูุน ู ูุฑูุญ ูุฎุฑูุฌุงุช ุงูุตูู\r\nโข - ุฎุงูุฉ ูููุฒุฉ ุจุชุฏู ุฌุณูู ุงูุณูุงุจูุฉ ุนุงููุฉ\r\nโข - 3 ุชูุดุฑุชุงุช ุจุงููุงู ูุฑุณููุงุช ูุฎุชููุฉ ุชูุฏุฑ ุชูุจุณูู ุจุฃูุชุฑ ูู ุดูู\r\nโข *ุงููุตู*\r\nโข - 3 ุชูุดูุฑุช ุจุฑุณููุงุช ุดุจุงุจู\r\nโข - ุฎุงูุฉ ูุทู ูุฎููุทุฉ ูููุฑุง\r\nโข - ููู ุจูุณู ู ุฑุณูุฉ ุจูุถุงุก ุจุณูุทุฉ ุนูู ุงูุตุฏุฑ\r\nโข - ุงูุฃููุงู ( ุงุณูุฏุ ุงุฎุถุฑุ ุงุตูุฑ )\r\nโข *ุงูููุงุณุงุช*\r\nโข - ููุงุณ : M\r\nโข ููุจุณ ูู 50 : 55 ูููู\r\nโข (ุนุฑุถ 50 ุณูุ ุงูุทูู 64 ุณู)\r\nโข - ููุงุณ : L\r\nโข ููุจุณ ูู 55 : 65 ูููู\r\nโข (ุงูุนุฑุถ 52 ุณูุ ุงูุทูู 66 ุณู)\r\nโข - ููุงุณ : XL\r\nโข ููุจุณ ูู 65 : 70 ูููู\r\nโข (ุงูุนุฑุถ 54 ุณูุ ุงูุทูู 68 ุณู)\r\nโข - ููุงุณ :2XL\r\nโข ููุจุณ ูู 70 : 75 ูููู\r\nโข (ุงูุนุฑุถ 56ุ ุงูุทูู 70 ุณู)\r\nโข *ุงููููุฒุงุช*\r\nโข - ุงุณุชุงูู ูุฑูุญ ู ุนููู\r\nโข - ุฎุงูุฉ ุทุฑูุฉ ูุฑูุญู ูู ุงููุจุณ ููุงุณุจุฉ ููุตูู\r\nโข - ุชุตูููู ุดูู ูุนูู ุงูููุถุฉ ุชูุฏุฑ ุชูุจุณู ูู ุฎุฑูุฌุงุชู ูุน ุตุญุงุจูุ ูู ุงููุงุฏู ู ููุงู ูู ุงูุฌุงูุนุฉ\r\nโข *ุงููุตู*\r\nโข - ุงูุฎุงูุฉ: ุจูุทููู ูููุชูู\r\nโข - ุงูุฃููุงู: (ูุญููุ ุฑูุงุฏูุ ุฃุณูุฏ)\r\nโข *ุงูููุงุณุงุช*\r\nโข ููุงุณ : L (ููุจุณ ูู 55 - 70 ูููู)\r\nโข ููุงุณ : XL (ููุจุณ ูู 70 - 80 ูููู)\r\nโข ููุงุณ :2XL (ููุจุณ ูู 80 - 95 ูููู)\r\nโข","hide":true,"media":["https://tager-uploads.s3.eu-central-1.amazonaws.com/bf8bf2ad-efc6-425d-8c53-b70dc062a7b0.jpg","https://tager-uploads.s3.eu-central-1.amazonaws.com/42a12a89-be66-45de-8a46-fa8ad315783d.jpg","https://tager-uploads.s3.eu-central-1.amazonaws.com/0e99ba91-0eb1-429c-aaa2-38a2ad94b44c.jpg","https://tager-uploads.s3.eu-central-1.amazonaws.com/b0bc6768-8817-4061-9491-ab7e26ecec37.jpg","https://tager-uploads.s3.eu-central-1.amazonaws.com/0b32e855-2166-4f57-931c-d1e6e1485e35.jpg","https://tager-uploads.s3.eu-central-1.amazonaws.com/a6c6bf79-20a5-40b4-bfc4-36f495c54478.jpg","https://tager-uploads.s3.eu-central-1.amazonaws.com/23e089c5-8133-4e13-837e-10069765d068.jpg"]},{"attr":[{"type":"size","value":"L","id":"EG020101VP0599"},{"type":"size","value":"XL","id":"EG020101VP0699"},{"type":"size","value":"XXL","id":"EG020101VP0799"}],"cat":{"name":"Taager exclusive offers","text":"ุนุฑูุถ ุชุงุฌุฑ ุงูุญุตุฑูุฉ"},"id":"EG020101VP0799","status":"available","desc":"ุนุฑุถ ุงูุตูู ูุงููุตูู ๐ุ ุงูุจุณ ุจุฑุงุญุชู ู ุงุชุดูู ูุน ุนุฑุถ 3 ุชูุดูุฑุช ุตููู Vintage + ุนุฑุถ 3 ุจูุทููู ูููุชูู ุตููู ุ ุฌูุนูุง ูู ุงูุชุฑ ูู ูุทุนู  ุนุดุงู ูููุฑ ูู ู ูุณูู ุนูููุ 6 ูุทุน ูู ุนุฑุถ ูุงุญุฏ ุจุณุนุฑ ููุชุนูุถุด ๐๐","title":"ุนุฑุถ 3 ุชูุดูุฑุช ุตููู Vintage + ุนุฑุถ 3 ุจูุทููู ูููุชูู ุตููู","price":300,"specs":"โข *ุงููููุฒุงุช*\r\nโข - ูููุฒ ุจุฑุณููุงุช ุนุตุฑูุฉ ุนูู ุงูููุถุฉ ุชุฎุทู ุงูุนูู ๐\r\nโข - ุณุฑูุน ู ูุฑูุญ ูุฎุฑูุฌุงุช ุงูุตูู\r\nโข - ุฎุงูุฉ ูููุฒุฉ ุจุชุฏู ุฌุณูู ุงูุณูุงุจูุฉ ุนุงููุฉ\r\nโข - 3 ุชูุดุฑุชุงุช ุจุงููุงู ูุฑุณููุงุช ูุฎุชููุฉ ุชูุฏุฑ ุชูุจุณูู ุจุฃูุชุฑ ูู ุดูู\r\nโข *ุงููุตู*\r\nโข - 3 ุชูุดูุฑุช ุจุฑุณููุงุช ุดุจุงุจู\r\nโข - ุฎุงูุฉ ูุทู ูุฎููุทุฉ ูููุฑุง\r\nโข - ููู ุจูุณู ู ุฑุณูุฉ ุจูุถุงุก ุจุณูุทุฉ ุนูู ุงูุตุฏุฑ\r\nโข - ุงูุฃููุงู ( ุงุณูุฏุ ุงุฎุถุฑุ ุงุตูุฑ )\r\nโข *ุงูููุงุณุงุช*\r\nโข - ููุงุณ : M\r\nโข ููุจุณ ูู 50 : 55 ูููู\r\nโข (ุนุฑุถ 50 ุณูุ ุงูุทูู 64 ุณู)\r\nโข - ููุงุณ : L\r\nโข ููุจุณ ูู 55 : 65 ูููู\r\nโข (ุงูุนุฑุถ 52 ุณูุ ุงูุทูู 66 ุณู)\r\nโข - ููุงุณ : XL\r\nโข ููุจุณ ูู 65 : 70 ูููู\r\nโข (ุงูุนุฑุถ 54 ุณูุ ุงูุทูู 68 ุณู)\r\nโข - ููุงุณ :2XL\r\nโข ููุจุณ ูู 70 : 75 ูููู\r\nโข (ุงูุนุฑุถ 56ุ ุงูุทูู 70 ุณู)\r\nโข *ุงููููุฒุงุช*\r\nโข - ุงุณุชุงูู ูุฑูุญ ู ุนููู\r\nโข - ุฎุงูุฉ ุทุฑูุฉ ูุฑูุญู ูู ุงููุจุณ ููุงุณุจุฉ ููุตูู\r\nโข - ุชุตูููู ุดูู ูุนูู ุงูููุถุฉ ุชูุฏุฑ ุชูุจุณู ูู ุฎุฑูุฌุงุชู ูุน ุตุญุงุจูุ ูู ุงููุงุฏู ู ููุงู ูู ุงูุฌุงูุนุฉ\r\nโข *ุงููุตู*\r\nโข - ุงูุฎุงูุฉ: ุจูุทููู ูููุชูู\r\nโข - ุงูุฃููุงู: (ูุญููุ ุฑูุงุฏูุ ุฃุณูุฏ)\r\nโข *ุงูููุงุณุงุช*\r\nโข ููุงุณ : L (ููุจุณ ูู 55 - 70 ูููู)\r\nโข ููุงุณ : XL (ููุจุณ ูู 70 - 80 ูููู)\r\nโข ููุงุณ :2XL (ููุจุณ ูู 80 - 95 ูููู)\r\nโข","hide":true,"media":["https://tager-uploads.s3.eu-central-1.amazonaws.com/dc1cfc35-db34-48c2-b3f0-95aff8c693fb.jpg","https://tager-uploads.s3.eu-central-1.amazonaws.com/a680dd38-3229-48b6-bd92-6c8674e104ee.jpg","https://tager-uploads.s3.eu-central-1.amazonaws.com/616f115c-35ad-492c-b6c3-93ce04612d05.jpg","https://tager-uploads.s3.eu-central-1.amazonaws.com/4f77c555-9a5a-4310-98b5-a691ebdd5980.jpg","https://tager-uploads.s3.eu-central-1.amazonaws.com/bc7e97f5-f4dd-4afa-bce4-8356670b3341.jpg","https://tager-uploads.s3.eu-central-1.amazonaws.com/c6380e9c-01b1-4c2b-a276-5885cd490348.jpg","https://tager-uploads.s3.eu-central-1.amazonaws.com/fa851ca5-c9d9-4268-a628-e840f68034b3.jpg","https://tager-uploads.s3.eu-central-1.amazonaws.com/a0475126-59bf-4860-855b-e147aafa5bb0.jpg"]},{"attr":[{"type":"size","value":"M","id":"EG020101VA0599"},{"type":"size","value":"L","id":"EG020101VA0699"},{"type":"size","value":"XL","id":"EG020101VA0799"}],"cat":{"name":"Taager exclusive offers","text":"ุนุฑูุถ ุชุงุฌุฑ ุงูุญุตุฑูุฉ"},"id":"EG020101VA0599","status":"available","desc":"ุนุดุงู ุดูุงูุชู ุฃูู ุญุงุฌุฉ ุฌุจูุงูู ุนุฑุถ ููููุด ุญุงุฌุฉ ูุงูุตุฉุ ุงุดุชุฑู 4 ุชูุดุฑุชุงุช v neck ุตููู ููุนุงูู ุณุงุนุฉ ุชุงุชุด ููุญูุธุฉ ุฌูุฏ ูุญุธุงุธุฉุ ูู ุฏู ุจุณุนุฑ ูุบุฑู ุฌุฏุง.","title":"ุณุงุนุฉ ุชุงุชุด ุฏุงุฆุฑูุฉ ุฃุณูุฏ + ุญุธุงุธุฉ ูุฏ ุจููู ูุนุฏู + ูุญูุธุฉ ุฑุฌุงูู + ุนุฑุถ 4 ุชูุดูุฑุช ุตูู V Neck","price":230,"specs":"โข *ุงููููุฒุงุช*\r\nโข - ุชูุดุฑุช ูุทู ูุฎููุท ูููุฑุง ูุฑูุญ ู ุทุฑู ุนูู ุงูุฌุณู\r\nโข - ูููุฑูู ูู ููู 4 ุงููุงู ุงุณุงุณูุฉ ููุจุณ\r\nโข - ุชูุฏุฑ ุชุณุชุบู ูู ููู ุจุงูุซุฑ ูู ุณุชุงูู\r\nโข *ุงูุชูุงุตูู*\r\nโข -ุงูููุฏูู: ุชูุดูุฑุช ุตููู V nick\r\nโข - ุงูุฎุงูุฉ: ูุทู ูููุฑุง\r\nโข - ุงูููู: ( ุงุจูุถุ ุงุณูุฏุ ูุญููุ ุฑูุงุฏู )\r\nโข - ูุงุจู ููุบุณูู ูู ุงูุบุณุงูุฉ\r\nโข - ุถุฏ ุงูุงูููุงุด / ุงููุงู ุซุงุจุชุฉ\r\nโข *ุงูููุงุณุงุช*\r\nโข - ููุงุณ : M\r\nโข ุชูุจูุณ ูู 50 - 60 ูููู\r\nโข (ุงูุนุฑุถ 48 ุงูุทูู 64)ุณู\r\nโข - ููุงุณ : L\r\nโข ุชูุจูุณ ูู 60 - 70 ูููู\r\nโข (ุงูุนุฑุถ 50 ุงูุทูู 66)ุณู\r\nโข - ููุงุณ : XL\r\nโข ุชูุจูุณ ูู 70 - 80 ูููู\r\nโข (ุงูุนุฑุถ 52 ุงูุทูู 67)ุณู\r\nโข - ููุงุณ :2XL\r\nโข ุชูุจูุณ ูู 80 - 90 ูููู\r\nโข (ุงูุนุฑุถ 54 ุงูุทูู 69)ุณู\r\nโข *ูููุฒุงุช ุงูุญุธุงุธุฉ*\r\nโข - ูุฎุชููุฉ ุชุถูู ููุณุฉ ุดูุงูุฉ ูุทููู\r\nโข - ุฎุงูุชูุง ููุชุงุฒุฉ ุจุชูุงุตูู ูููุฒุฉ ูุฑูุญุฉ ูู ุงูุงูุฏ ูุด ูุชุถุงููู\r\nโข *ุงููุตู*\r\nโข ุงูุฎุงูุฉ: ุฌูุฏ\r\nโข ุงูููู: ูุนุฏู\r\nโข ุงูููู: ุฃุณูุฏ\r\nโข *ูููุฒุงุช ุงููุญูุธุฉ*\r\nโข - ุฎุงูุชูุง ุนุงููุฉ ุฌุฏุง ูุด ูุชุชูุดุฑ ุจุณูููุฉ\r\nโข - ูููุง ุฌูุจ ุจุณูุณุชู ุชูุฏุฑ ุชุญุท ูู ุงููููุณ ูุงููุฑู ุงูููู ูู ุบูุฑ ูุง ุชููู\r\nโข - ูููุง ุญุงูุธุฉ ูุฑูุช ูุนูู ูุด ูุชุญุชุงุฌ ุชุดูู ูุญูุธุฉ ู ุญุงูุธุฉ ูุฑูุช\r\nโข - ูููุง ููู ูุบูุงุทูุณู ูุด ููุฎูู ุญุงุฌู ุชูุน ูููุง\r\nโข - ูููุง ุงูุชุฑ ูู ููุงู ุชูุฏุฑ ุชุญุท ููู ูุฑูุชู ุงูุดุฎุตูุฉ ู ุงูุชุฑ ูู ููุฒุง\r\nโข *ูููุฒุงุช ุงูุณุงุนุฉ ุงูุชุงุชุด*\r\nโข - ุจุชุดุชุบู ุจุญุฌุงุฑุฉ ุณุงุนุฉ \r\nโข - ูุฑูุญุฉ ุฌุฏุง ู ุดูู ูุน ูู ุงูุงุทูู\r\nโข - ุงุณุชูู ููุงุณุจ ููู ูุฏ\r\nโข *ูุตู ุงูุณุงุนุฉ* \r\nโข - ุงูุฎุงูุฉ: ูุนุฏู.\r\nโข - ุงูููู: ( ุฃุณูุฏ)\r\nโข - ุงูุงุณุชุฎุฏุงู ุชุงุชุด.\r\nโข","media":["https://tager-uploads.s3.eu-central-1.amazonaws.com/ef33a0f9-06e3-4731-9057-464a36dcbc56.jpg","https://tager-uploads.s3.eu-central-1.amazonaws.com/a1537240-d62a-4fde-8b87-64fd6610b185.jpg","https://tager-uploads.s3.eu-central-1.amazonaws.com/7fe34688-82e5-452d-935d-0fa01c5a1d76.jpg","https://tager-uploads.s3.eu-central-1.amazonaws.com/e40f9f78-6033-4db8-87c6-5d626b2e781e.jpg","https://tager-uploads.s3.eu-central-1.amazonaws.com/686d38df-9e6f-4658-9868-80401e3d046e.jpg","https://tager-uploads.s3.eu-central-1.amazonaws.com/2391b0e0-3f1a-44e4-8517-311845055a72.jpg"]},{"attr":[{"type":"size","value":"M","id":"EG020101VA0599"},{"type":"size","value":"L","id":"EG020101VA0699"},{"type":"size","value":"XL","id":"EG020101VA0799"}],"cat":{"name":"Taager exclusive offers","text":"ุนุฑูุถ ุชุงุฌุฑ ุงูุญุตุฑูุฉ"},"id":"EG020101VA0699","status":"available","desc":"ุนุดุงู ุดูุงูุชู ุฃูู ุญุงุฌุฉ ุฌุจูุงูู ุนุฑุถ ููููุด ุญุงุฌุฉ ูุงูุตุฉุ ุงุดุชุฑู 4 ุชูุดุฑุชุงุช v neck ุตููู ููุนุงูู ุณุงุนุฉ ุชุงุชุด ููุญูุธุฉ ุฌูุฏ ูุญุธุงุธุฉุ ูู ุฏู ุจุณุนุฑ ูุบุฑู ุฌุฏุง.","title":"ุณุงุนุฉ ุชุงุชุด ุฏุงุฆุฑูุฉ ุฃุณูุฏ + ุญุธุงุธุฉ ูุฏ ุจููู ูุนุฏู + ูุญูุธุฉ ุฑุฌุงูู + ุนุฑุถ 4 ุชูุดูุฑุช ุตูู V Neck","price":230,"specs":"โข *ุงููููุฒุงุช*\r\nโข - ุชูุดุฑุช ูุทู ูุฎููุท ูููุฑุง ูุฑูุญ ู ุทุฑู ุนูู ุงูุฌุณู\r\nโข - ูููุฑูู ูู ููู 4 ุงููุงู ุงุณุงุณูุฉ ููุจุณ\r\nโข - ุชูุฏุฑ ุชุณุชุบู ูู ููู ุจุงูุซุฑ ูู ุณุชุงูู\r\nโข *ุงูุชูุงุตูู*\r\nโข -ุงูููุฏูู: ุชูุดูุฑุช ุตููู V nick\r\nโข - ุงูุฎุงูุฉ: ูุทู ูููุฑุง\r\nโข - ุงูููู: ( ุงุจูุถุ ุงุณูุฏุ ูุญููุ ุฑูุงุฏู )\r\nโข - ูุงุจู ููุบุณูู ูู ุงูุบุณุงูุฉ\r\nโข - ุถุฏ ุงูุงูููุงุด / ุงููุงู ุซุงุจุชุฉ\r\nโข *ุงูููุงุณุงุช*\r\nโข - ููุงุณ : M\r\nโข ุชูุจูุณ ูู 50 - 60 ูููู\r\nโข (ุงูุนุฑุถ 48 ุงูุทูู 64)ุณู\r\nโข - ููุงุณ : L\r\nโข ุชูุจูุณ ูู 60 - 70 ูููู\r\nโข (ุงูุนุฑุถ 50 ุงูุทูู 66)ุณู\r\nโข - ููุงุณ : XL\r\nโข ุชูุจูุณ ูู 70 - 80 ูููู\r\nโข (ุงูุนุฑุถ 52 ุงูุทูู 67)ุณู\r\nโข - ููุงุณ :2XL\r\nโข ุชูุจูุณ ูู 80 - 90 ูููู\r\nโข (ุงูุนุฑุถ 54 ุงูุทูู 69)ุณู\r\nโข *ูููุฒุงุช ุงูุญุธุงุธุฉ*\r\nโข - ูุฎุชููุฉ ุชุถูู ููุณุฉ ุดูุงูุฉ ูุทููู\r\nโข - ุฎุงูุชูุง ููุชุงุฒุฉ ุจุชูุงุตูู ูููุฒุฉ ูุฑูุญุฉ ูู ุงูุงูุฏ ูุด ูุชุถุงููู\r\nโข *ุงููุตู*\r\nโข ุงูุฎุงูุฉ: ุฌูุฏ\r\nโข ุงูููู: ูุนุฏู\r\nโข ุงูููู: ุฃุณูุฏ\r\nโข *ูููุฒุงุช ุงููุญูุธุฉ*\r\nโข - ุฎุงูุชูุง ุนุงููุฉ ุฌุฏุง ูุด ูุชุชูุดุฑ ุจุณูููุฉ\r\nโข - ูููุง ุฌูุจ ุจุณูุณุชู ุชูุฏุฑ ุชุญุท ูู ุงููููุณ ูุงููุฑู ุงูููู ูู ุบูุฑ ูุง ุชููู\r\nโข - ูููุง ุญุงูุธุฉ ูุฑูุช ูุนูู ูุด ูุชุญุชุงุฌ ุชุดูู ูุญูุธุฉ ู ุญุงูุธุฉ ูุฑูุช\r\nโข - ูููุง ููู ูุบูุงุทูุณู ูุด ููุฎูู ุญุงุฌู ุชูุน ูููุง\r\nโข - ูููุง ุงูุชุฑ ูู ููุงู ุชูุฏุฑ ุชุญุท ููู ูุฑูุชู ุงูุดุฎุตูุฉ ู ุงูุชุฑ ูู ููุฒุง\r\nโข *ูููุฒุงุช ุงูุณุงุนุฉ ุงูุชุงุชุด*\r\nโข - ุจุชุดุชุบู ุจุญุฌุงุฑุฉ ุณุงุนุฉ \r\nโข - ูุฑูุญุฉ ุฌุฏุง ู ุดูู ูุน ูู ุงูุงุทูู\r\nโข - ุงุณุชูู ููุงุณุจ ููู ูุฏ\r\nโข *ูุตู ุงูุณุงุนุฉ* \r\nโข - ุงูุฎุงูุฉ: ูุนุฏู.\r\nโข - ุงูููู: ( ุฃุณูุฏ)\r\nโข - ุงูุงุณุชุฎุฏุงู ุชุงุชุด.\r\nโข","hide":true,"media":["https://tager-uploads.s3.eu-central-1.amazonaws.com/11aa9bda-d8c1-4090-bbcd-5167bd76159e.jpg","https://tager-uploads.s3.eu-central-1.amazonaws.com/d6c6c626-50b2-496c-aa94-f68017c65e7a.jpg","https://tager-uploads.s3.eu-central-1.amazonaws.com/15d80d1e-51d1-430e-b97a-882c38fa9d55.jpg","https://tager-uploads.s3.eu-central-1.amazonaws.com/5976c10b-0e6e-40ec-b897-24d583cf3e81.jpg","https://tager-uploads.s3.eu-central-1.amazonaws.com/50c0e5b0-ffe9-4b24-b001-389987e4669b.jpg","https://tager-uploads.s3.eu-central-1.amazonaws.com/6f509ced-62ce-4480-b352-df49238741a4.jpg"]},{"attr":[{"type":"size","value":"M","id":"EG020101VA0599"},{"type":"size","value":"L","id":"EG020101VA0699"},{"type":"size","value":"XL","id":"EG020101VA0799"}],"cat":{"name":"Taager exclusive offers","text":"ุนุฑูุถ ุชุงุฌุฑ ุงูุญุตุฑูุฉ"},"id":"EG020101VA0799","status":"available","desc":"ุนุดุงู ุดูุงูุชู ุฃูู ุญุงุฌุฉ ุฌุจูุงูู ุนุฑุถ ููููุด ุญุงุฌุฉ ูุงูุตุฉุ ุงุดุชุฑู 4 ุชูุดุฑุชุงุช v neck ุตููู ููุนุงูู ุณุงุนุฉ ุชุงุชุด ููุญูุธุฉ ุฌูุฏ ูุญุธุงุธุฉุ ูู ุฏู ุจุณุนุฑ ูุบุฑู ุฌุฏุง.","title":"ุณุงุนุฉ ุชุงุชุด ุฏุงุฆุฑูุฉ ุฃุณูุฏ + ุญุธุงุธุฉ ูุฏ ุจููู ูุนุฏู + ูุญูุธุฉ ุฑุฌุงูู + ุนุฑุถ 4 ุชูุดูุฑุช ุตูู V Neck","price":230,"specs":"โข *ุงููููุฒุงุช*\r\nโข - ุชูุดุฑุช ูุทู ูุฎููุท ูููุฑุง ูุฑูุญ ู ุทุฑู ุนูู ุงูุฌุณู\r\nโข - ูููุฑูู ูู ููู 4 ุงููุงู ุงุณุงุณูุฉ ููุจุณ\r\nโข - ุชูุฏุฑ ุชุณุชุบู ูู ููู ุจุงูุซุฑ ูู ุณุชุงูู\r\nโข *ุงูุชูุงุตูู*\r\nโข -ุงูููุฏูู: ุชูุดูุฑุช ุตููู V nick\r\nโข - ุงูุฎุงูุฉ: ูุทู ูููุฑุง\r\nโข - ุงูููู: ( ุงุจูุถุ ุงุณูุฏุ ูุญููุ ุฑูุงุฏู )\r\nโข - ูุงุจู ููุบุณูู ูู ุงูุบุณุงูุฉ\r\nโข - ุถุฏ ุงูุงูููุงุด / ุงููุงู ุซุงุจุชุฉ\r\nโข *ุงูููุงุณุงุช*\r\nโข - ููุงุณ : M\r\nโข ุชูุจูุณ ูู 50 - 60 ูููู\r\nโข (ุงูุนุฑุถ 48 ุงูุทูู 64)ุณู\r\nโข - ููุงุณ : L\r\nโข ุชูุจูุณ ูู 60 - 70 ูููู\r\nโข (ุงูุนุฑุถ 50 ุงูุทูู 66)ุณู\r\nโข - ููุงุณ : XL\r\nโข ุชูุจูุณ ูู 70 - 80 ูููู\r\nโข (ุงูุนุฑุถ 52 ุงูุทูู 67)ุณู\r\nโข - ููุงุณ :2XL\r\nโข ุชูุจูุณ ูู 80 - 90 ูููู\r\nโข (ุงูุนุฑุถ 54 ุงูุทูู 69)ุณู\r\nโข *ูููุฒุงุช ุงูุญุธุงุธุฉ*\r\nโข - ูุฎุชููุฉ ุชุถูู ููุณุฉ ุดูุงูุฉ ูุทููู\r\nโข - ุฎุงูุชูุง ููุชุงุฒุฉ ุจุชูุงุตูู ูููุฒุฉ ูุฑูุญุฉ ูู ุงูุงูุฏ ูุด ูุชุถุงููู\r\nโข *ุงููุตู*\r\nโข ุงูุฎุงูุฉ: ุฌูุฏ\r\nโข ุงูููู: ูุนุฏู\r\nโข ุงูููู: ุฃุณูุฏ\r\nโข *ูููุฒุงุช ุงููุญูุธุฉ*\r\nโข - ุฎุงูุชูุง ุนุงููุฉ ุฌุฏุง ูุด ูุชุชูุดุฑ ุจุณูููุฉ\r\nโข - ูููุง ุฌูุจ ุจุณูุณุชู ุชูุฏุฑ ุชุญุท ูู ุงููููุณ ูุงููุฑู ุงูููู ูู ุบูุฑ ูุง ุชููู\r\nโข - ูููุง ุญุงูุธุฉ ูุฑูุช ูุนูู ูุด ูุชุญุชุงุฌ ุชุดูู ูุญูุธุฉ ู ุญุงูุธุฉ ูุฑูุช\r\nโข - ูููุง ููู ูุบูุงุทูุณู ูุด ููุฎูู ุญุงุฌู ุชูุน ูููุง\r\nโข - ูููุง ุงูุชุฑ ูู ููุงู ุชูุฏุฑ ุชุญุท ููู ูุฑูุชู ุงูุดุฎุตูุฉ ู ุงูุชุฑ ูู ููุฒุง\r\nโข *ูููุฒุงุช ุงูุณุงุนุฉ ุงูุชุงุชุด*\r\nโข - ุจุชุดุชุบู ุจุญุฌุงุฑุฉ ุณุงุนุฉ \r\nโข - ูุฑูุญุฉ ุฌุฏุง ู ุดูู ูุน ูู ุงูุงุทูู\r\nโข - ุงุณุชูู ููุงุณุจ ููู ูุฏ\r\nโข *ูุตู ุงูุณุงุนุฉ* \r\nโข - ุงูุฎุงูุฉ: ูุนุฏู.\r\nโข - ุงูููู: ( ุฃุณูุฏ)\r\nโข - ุงูุงุณุชุฎุฏุงู ุชุงุชุด.\r\nโข","hide":true,"media":["https://tager-uploads.s3.eu-central-1.amazonaws.com/1dd1e529-c703-4d64-94c5-e030c7d18f24.jpg","https://tager-uploads.s3.eu-central-1.amazonaws.com/69da1ae4-e314-4c99-8ecb-f5ae16175c32.jpg","https://tager-uploads.s3.eu-central-1.amazonaws.com/eff4f6b2-e5d8-4fb6-9096-d4ef9e096093.jpg","https://tager-uploads.s3.eu-central-1.amazonaws.com/31f5c3aa-2793-47f2-9d70-756e2d37095b.jpg","https://tager-uploads.s3.eu-central-1.amazonaws.com/e595571b-e946-4677-be4e-487b4d966912.jpg","https://tager-uploads.s3.eu-central-1.amazonaws.com/5b9387da-8d3f-4bb0-9797-feeb31f83eea.jpg"]},{"cat":{"name":"Taager exclusive offers","text":"ุนุฑูุถ ุชุงุฌุฑ ุงูุญุตุฑูุฉ"},"id":"EG040501STM499","status":"available","desc":"ุงููู ุนุฑุถ ููุชุฃูู ูุชุญูู ู ุชูุฑุฏ ูุญูุชู ู ุชุญุฏุฏูุง ูู ุฏู ูุดุท ุงูุดุนุฑ StylerV2 +ูุงูููุฉ ุญูุงูุฉ Max Brawn MP-802 + ุฃุฏุงุฉ ุชุญุฏูุฏ ุงูุฏูู ุงูุนุฌูุจุฉ.","title":"ูุดุท ุงูุดุนุฑ StylerV2 +ูุงูููุฉ ุญูุงูุฉ Max Brawn MP-802 + ุงุฏุงุฉ ุชุญุฏูุฏ ุงูุฏูู ุงูุนุฌูุจุฉ","price":200,"specs":"โข * ูููุฒุงุช ูุดุท ุงูุดุนุฑ Style V2 *\r\nโข ุฃูู ูุตูู ุดุนุฑ ูุนูู ุนูู ุชุตููู ุงูุดุนุฑ ูุงููุญูุฉ ุจุทุฑููุฉ ูุนุงูุฉ ูุขููุฉ.\r\nโข ููุญููู ุดุนุฑู ููุญูุชู ูู ูุฌุนุฏ ูุซูู ู ูุงุนู ูุณูุณ.\r\nโข ุงูุฌูุงุฒ ุฎููู ู ูุชุนุฑู ุชุงุฎุฏู ูุนุงู ููุช ุงูุณูุฑ.\r\nโข ุทูู ุงูุณูู ุทููู ุนูุดุงู ุชุนุฑู ุชุชุญุฑู ุจุฑุงุญุชู.\r\nโข ูุตู ูุดุท ุงูุดุนุฑ Style V2 *\r\nโข ุงูููู:- ุนุดูุงุฆู.\r\nโข ุงูุทุงูุฉ:- AC110-220V\\60.\r\nโข ุงูููุฉ:- W10\\112.\r\nโข ุทูู ุงูุณูู: 120 ุณู.\r\nโข ุงูุฃุจุนุงุฏ:- 22.5 ุงูุทูู.\r\nโข ุงูุฎุงูุฉ:- ุจูุงุณุชูู\r\nโข *ูุญุชูู ุนุจูุฉ ูุดุท ุงูุดุนุฑ Style V2*\r\nโข 1ร ูููุงุฉ\r\nโข * ูููุฒุงุช ูุงูููุฉ ุญูุงูุฉ Max Brawn MP-802 *\r\nโข ุงูุดูุฑุงุช ูู ุงูุฃุณุชุงููุณ ุณุชูู ุงูููุงูู ููุตุฏุฃ.\r\nโข ูุนุงูุง 3 ูุดุท ุจุฏุฑุฌุงุช ุดุนุฑ ูุฎุชููุฉ (3-6-9)ูู.\r\nโข ุจุทุงุฑูุฉ ูุงุจูุฉ ูุฅุนุงุฏุฉ ุงูุดุญู ููุนุงู ูุตูุฉ ููุดุญู.\r\nโข ูุนุงู ุงูุฒูุช ุงูุฎุงุต ุจูู ุนูุดุงู ุชุดุชุบู ุจุณูููุฉ.\r\nโข ุณููุฉ ุงูุชูุธูู ูุนุงูุง ูุฑุดุงุฉ ูุชูุถูู ุงูุดูุฑุงุช.\r\nโข * ูุตู ูุงูููุฉ ุญูุงูุฉ Max Brawn MP-802 *\r\nโข ุงููุงุฑูุฉ:- Max Brawn.\r\nโข ุงูููุฏูู:- MP-802.\r\nโข ุงูุทุงูุฉ:- 3 ูุงุช.\r\nโข ุงูุฌูุฏ:- 220\\240V.\r\nโข ุงูุชุฑุฏุฏ:- 50\\60HZ.\r\nโข ููุช ุงูุดุญู:- 12 ุณุงุนุฉ.\r\nโข ููุช ุงูุชุดุบูู:- 45 ุฏูููุฉ.\r\nโข ุงูุจุทุงุฑูุฉ:- 100MA.\r\nโข *ูุญุชูู ุงูุนุจูุฉ*\r\nโข 3รูุดุท.\r\nโข 1รูุงูููุฉ.\r\nโข 1รุฒูุช.\r\nโข รูุฑุดุงุฉ.\r\nโข 1รูุตูุฉ.\r\nโข * ูููุฒุงุช ุฃุฏุงุฉ ุชุญุฏูุฏ ุงูุฏูู ุงูุนุฌูุจุฉ *\r\nโข ูููุง 2 ุฎุท ูุชุญุฏูุฏ ุดูู ุงููุญูุฉ ูุงุญุฏ ููุญูู + ูุณุชููู ุนุดุงู ุชุฎุชุงุฑ ุงูููุงุณุจ ุนููู.\r\nโข ูููุง ูุฑุจุนุงุช ู ุฏู ุจุชุณุงุนุฏ ุนูู ุงูููุงุณ ุจุดูู ูุซุงูู.\r\nโข 2 ูุดุท ูุณุงุนุฏ ุนูู ูุฑุฏ ุงููุญูุฉ.\r\nโข ุฎุงูุชูุง ูุชููุฉ ููููุฉ.\r\nโข *ูุตู ุฃุฏุงุฉ ุชุญุฏูุฏ ุงูุฏูู ุงูุนุฌูุจุฉ*\r\nโข ุงูุฎุงูุฉ:- ุจูุงุณุชูู.\r\nโข ุงูุฃุจุนุงุฏ:-6.8ร11.5 ุณู.\r\nโข","media":["https://tager-uploads.s3.eu-central-1.amazonaws.com/ea57e870-fb5c-45ce-9f95-c9cf23048a50.jpg"]},{"attr":[{"type":"size","value":"32","id":"EG020103OJ3200"},{"type":"size","value":"34","id":"EG020103OJ3400"},{"type":"size","value":"36","id":"EG020103OJ3600"},{"type":"size","value":"38","id":"EG020103OJ3800"},{"type":"size","value":"40","id":"EG020103OJ4000"}],"cat":{"name":"Taager exclusive offers","text":"ุนุฑูุถ ุชุงุฌุฑ ุงูุญุตุฑูุฉ"},"id":"EG020103OJ3200","status":"available","desc":"ุฌุจูุงูู ุนุฑุถ ุงูุชูููุฑ 3๐ุ ุจูุทูููุงุช ุฌููุฒ ุจุงููุงู ุงุณุงุณูุฉ ูุงุฒู ุชููู ูู ุฏููุงุจูุ ููุงุณุจุฉ ู ูุงููุฉ ุนูู ูู ูุจุณู ุจุฎุงูุฉ ููุชุงุฒุฉ ู ุณุนุฑ ููุชุนูุถุด ุงูุญู ุงูุนุฑุถ ๐๐","title":"ูฃ ุฌููุฒ ุจูุฒูู","price":420,"specs":"โข *ุงูุชูุงุตูู*\r\nโข - ุงูููุฏูู : 3 ุฌููุฒ ุจูุฒูู \r\nโข - ุงูุฎุงูุฉ: ุฌููุฒ\r\nโข - ุงูููู: ( ุชูุฌู - ูุญูู - ูุญูู ูุงุชุญ )\r\nโข - ุงุฒุฑุงุฑ\r\nโข - (2 ุฌูุจ ุฃูุงููุ 2 ุฌูุจ ุฎููู)\r\nโข - ุงููุงู ุนูููุฉ ู ููุงุณุจุฉ\r\nโข *ููุงุณุงุช*\r\nโข - ููุงุณ 32 ููุจุณ ูู 55 - 65 ูููู\r\nโข ( ุทูู 106 ุณูุ ุนุฑุถ ุงููุณุท 40 ุณูุ ุทูู ุงูุญุฌุฑ 29 ุณูุ ุนุฑุถ ุงูุญุฌุฑ 50 ุณู)\r\nโข - ููุงุณ 34 ููุจุณ ูู 65 - 75 ูููู\r\nโข ( ุทูู 107 ุณูุ ุนุฑุถ ุงููุณุท 42 ุณูุ ุทูู ุงูุญุฌุฑ 29 ุณูุ ุนุฑุถ ุงูุญุฌุฑ 52 ุณู)\r\nโข - ููุงุณ 36 ููุจุณ ูู 75 - 85 ูููู\r\nโข ( ุทูู 108 ุณูุ ุนุฑุถ ุงููุณุท 44 ุณูุ ุทูู ุงูุญุฌุฑ 29 ุณูุ ุนุฑุถ ุงูุญุฌุฑ 54 ุณู)\r\nโข - ููุงุณ 38 ููุจุณ ูู 85 - 95 ูููู\r\nโข ( ุทูู 109 ุณูุ ุนุฑุถ ุงููุณุท 46 ุณูุ ุทูู ุงูุญุฌุฑ 29 ุณูุ ุนุฑุถ ุงูุญุฌุฑ 56 ุณู)\r\nโข - ููุงุณ 40 ููุจุณ ูู 95 - 100 ูููู\r\nโข ( ุทูู 110 ุณูุ ุนุฑุถ ุงููุณุท 48 ุณูุ ุทูู ุงูุญุฌุฑ 29 ุณูุ ุนุฑุถ ุงูุญุฌุฑ 58 ุณู)\r\nโข *ุงูุฎุงูุฉ ู ุงูุงุณุชุฎุฏุงู*\r\nโข - ุฌููุฒ/ ูููุฑุง\r\nโข - ูุนุงูุฌ ุถุฏ ุงูุงูููุงุด\r\nโข - ุงููุงู ุซุงุจุชุฉ\r\nโข - ูุงุจู ููุบุณู ูู ุงูุบุณุงูุฉ\r\nโข","media":["https://tager-uploads.s3.eu-central-1.amazonaws.com/37b4bc66-776c-44b2-9b1b-8388915b704d.jpg","https://tager-uploads.s3.eu-central-1.amazonaws.com/44c2d233-d391-4b3a-8747-e260bf0536b8.jpg","https://tager-uploads.s3.eu-central-1.amazonaws.com/c34b9583-9235-4635-9842-b1b75555f626.jpg","https://tager-uploads.s3.eu-central-1.amazonaws.com/78ea74dc-e649-4ecb-9a08-b5b1c8ef9a8c.jpg","https://tager-uploads.s3.eu-central-1.amazonaws.com/43df855f-f46c-4e03-a9b7-ae8b78dddee5.jpg","https://tager-uploads.s3.eu-central-1.amazonaws.com/5f0f98c9-7ced-4284-8f18-9ed17b4ea22b.jpg"]},{"attr":[{"type":"size","value":"32","id":"EG020103OJ3200"},{"type":"size","value":"34","id":"EG020103OJ3400"},{"type":"size","value":"36","id":"EG020103OJ3600"},{"type":"size","value":"38","id":"EG020103OJ3800"},{"type":"size","value":"40","id":"EG020103OJ4000"}],"cat":{"name":"Taager exclusive offers","text":"ุนุฑูุถ ุชุงุฌุฑ ุงูุญุตุฑูุฉ"},"id":"EG020103OJ3400","status":"available","desc":"ุฌุจูุงูู ุนุฑุถ ุงูุชูููุฑ 3๐ุ ุจูุทูููุงุช ุฌููุฒ ุจุงููุงู ุงุณุงุณูุฉ ูุงุฒู ุชููู ูู ุฏููุงุจูุ ููุงุณุจุฉ ู ูุงููุฉ ุนูู ูู ูุจุณู ุจุฎุงูุฉ ููุชุงุฒุฉ ู ุณุนุฑ ููุชุนูุถุด ุงูุญู ุงูุนุฑุถ ๐๐","title":"ูฃ ุฌููุฒ ุจูุฒูู","price":420,"specs":"โข *ุงูุชูุงุตูู*\r\nโข - ุงูููุฏูู : 3 ุฌููุฒ ุจูุฒูู \r\nโข - ุงูุฎุงูุฉ: ุฌููุฒ\r\nโข - ุงูููู: ( ุชูุฌู - ูุญูู - ูุญูู ูุงุชุญ )\r\nโข - ุงุฒุฑุงุฑ\r\nโข - (2 ุฌูุจ ุฃูุงููุ 2 ุฌูุจ ุฎููู)\r\nโข - ุงููุงู ุนูููุฉ ู ููุงุณุจุฉ\r\nโข *ููุงุณุงุช*\r\nโข - ููุงุณ 32 ููุจุณ ูู 55 - 65 ูููู\r\nโข ( ุทูู 106 ุณูุ ุนุฑุถ ุงููุณุท 40 ุณูุ ุทูู ุงูุญุฌุฑ 29 ุณูุ ุนุฑุถ ุงูุญุฌุฑ 50 ุณู)\r\nโข - ููุงุณ 34 ููุจุณ ูู 65 - 75 ูููู\r\nโข ( ุทูู 107 ุณูุ ุนุฑุถ ุงููุณุท 42 ุณูุ ุทูู ุงูุญุฌุฑ 29 ุณูุ ุนุฑุถ ุงูุญุฌุฑ 52 ุณู)\r\nโข - ููุงุณ 36 ููุจุณ ูู 75 - 85 ูููู\r\nโข ( ุทูู 108 ุณูุ ุนุฑุถ ุงููุณุท 44 ุณูุ ุทูู ุงูุญุฌุฑ 29 ุณูุ ุนุฑุถ ุงูุญุฌุฑ 54 ุณู)\r\nโข - ููุงุณ 38 ููุจุณ ูู 85 - 95 ูููู\r\nโข ( ุทูู 109 ุณูุ ุนุฑุถ ุงููุณุท 46 ุณูุ ุทูู ุงูุญุฌุฑ 29 ุณูุ ุนุฑุถ ุงูุญุฌุฑ 56 ุณู)\r\nโข - ููุงุณ 40 ููุจุณ ูู 95 - 100 ูููู\r\nโข ( ุทูู 110 ุณูุ ุนุฑุถ ุงููุณุท 48 ุณูุ ุทูู ุงูุญุฌุฑ 29 ุณูุ ุนุฑุถ ุงูุญุฌุฑ 58 ุณู)\r\nโข *ุงูุฎุงูุฉ ู ุงูุงุณุชุฎุฏุงู*\r\nโข - ุฌููุฒ/ ูููุฑุง\r\nโข - ูุนุงูุฌ ุถุฏ ุงูุงูููุงุด\r\nโข - ุงููุงู ุซุงุจุชุฉ\r\nโข - ูุงุจู ููุบุณู ูู ุงูุบุณุงูุฉ\r\nโข","hide":true,"media":["https://tager-uploads.s3.eu-central-1.amazonaws.com/2c4ff4a6-9fa6-47ff-b630-ba53726ac881.jpg","https://tager-uploads.s3.eu-central-1.amazonaws.com/3a078f08-1a44-45a9-befc-3a0750f63711.jpg","https://tager-uploads.s3.eu-central-1.amazonaws.com/12fcf673-9158-4ef4-a1a1-2d22851d4abd.jpg","https://tager-uploads.s3.eu-central-1.amazonaws.com/8865f435-41b4-4572-9492-59364121f112.jpg","https://tager-uploads.s3.eu-central-1.amazonaws.com/1a6454e3-840c-4ebd-8879-ff0b05790c84.jpg","https://tager-uploads.s3.eu-central-1.amazonaws.com/eb4f0824-363e-463f-84b5-6d77f801ceb0.jpg"]},{"attr":[{"type":"size","value":"32","id":"EG020103OJ3200"},{"type":"size","value":"34","id":"EG020103OJ3400"},{"type":"size","value":"36","id":"EG020103OJ3600"},{"type":"size","value":"38","id":"EG020103OJ3800"},{"type":"size","value":"40","id":"EG020103OJ4000"}],"cat":{"name":"Taager exclusive offers","text":"ุนุฑูุถ ุชุงุฌุฑ ุงูุญุตุฑูุฉ"},"id":"EG020103OJ3600","status":"available","desc":"ุฌุจูุงูู ุนุฑุถ ุงูุชูููุฑ 3๐ุ ุจูุทูููุงุช ุฌููุฒ ุจุงููุงู ุงุณุงุณูุฉ ูุงุฒู ุชููู ูู ุฏููุงุจูุ ููุงุณุจุฉ ู ูุงููุฉ ุนูู ูู ูุจุณู ุจุฎุงูุฉ ููุชุงุฒุฉ ู ุณุนุฑ ููุชุนูุถุด ุงูุญู ุงูุนุฑุถ ๐๐","title":"ูฃ ุฌููุฒ ุจูุฒูู","price":420,"specs":"โข *ุงูุชูุงุตูู*\r\nโข - ุงูููุฏูู : 3 ุฌููุฒ ุจูุฒูู \r\nโข - ุงูุฎุงูุฉ: ุฌููุฒ\r\nโข - ุงูููู: ( ุชูุฌู - ูุญูู - ูุญูู ูุงุชุญ )\r\nโข - ุงุฒุฑุงุฑ\r\nโข - (2 ุฌูุจ ุฃูุงููุ 2 ุฌูุจ ุฎููู)\r\nโข - ุงููุงู ุนูููุฉ ู ููุงุณุจุฉ\r\nโข *ููุงุณุงุช*\r\nโข - ููุงุณ 32 ููุจุณ ูู 55 - 65 ูููู\r\nโข ( ุทูู 106 ุณูุ ุนุฑุถ ุงููุณุท 40 ุณูุ ุทูู ุงูุญุฌุฑ 29 ุณูุ ุนุฑุถ ุงูุญุฌุฑ 50 ุณู)\r\nโข - ููุงุณ 34 ููุจุณ ูู 65 - 75 ูููู\r\nโข ( ุทูู 107 ุณูุ ุนุฑุถ ุงููุณุท 42 ุณูุ ุทูู ุงูุญุฌุฑ 29 ุณูุ ุนุฑุถ ุงูุญุฌุฑ 52 ุณู)\r\nโข - ููุงุณ 36 ููุจุณ ูู 75 - 85 ูููู\r\nโข ( ุทูู 108 ุณูุ ุนุฑุถ ุงููุณุท 44 ุณูุ ุทูู ุงูุญุฌุฑ 29 ุณูุ ุนุฑุถ ุงูุญุฌุฑ 54 ุณู)\r\nโข - ููุงุณ 38 ููุจุณ ูู 85 - 95 ูููู\r\nโข ( ุทูู 109 ุณูุ ุนุฑุถ ุงููุณุท 46 ุณูุ ุทูู ุงูุญุฌุฑ 29 ุณูุ ุนุฑุถ ุงูุญุฌุฑ 56 ุณู)\r\nโข - ููุงุณ 40 ููุจุณ ูู 95 - 100 ูููู\r\nโข ( ุทูู 110 ุณูุ ุนุฑุถ ุงููุณุท 48 ุณูุ ุทูู ุงูุญุฌุฑ 29 ุณูุ ุนุฑุถ ุงูุญุฌุฑ 58 ุณู)\r\nโข *ุงูุฎุงูุฉ ู ุงูุงุณุชุฎุฏุงู*\r\nโข - ุฌููุฒ/ ูููุฑุง\r\nโข - ูุนุงูุฌ ุถุฏ ุงูุงูููุงุด\r\nโข - ุงููุงู ุซุงุจุชุฉ\r\nโข - ูุงุจู ููุบุณู ูู ุงูุบุณุงูุฉ\r\nโข","hide":true,"media":["https://tager-uploads.s3.eu-central-1.amazonaws.com/6e0c1633-4439-490c-a68f-112a3a9ea7d6.jpg","https://tager-uploads.s3.eu-central-1.amazonaws.com/d7d1892c-f233-406e-96ba-e182dbc23b2d.jpg","https://tager-uploads.s3.eu-central-1.amazonaws.com/79d77295-9e55-4897-93be-67701d630703.jpg","https://tager-uploads.s3.eu-central-1.amazonaws.com/2f7f989c-03fe-48f8-896f-578bd99a2d19.jpg","https://tager-uploads.s3.eu-central-1.amazonaws.com/06ab527a-fa83-40aa-aa9c-1faf9ed04ce5.jpg","https://tager-uploads.s3.eu-central-1.amazonaws.com/9a8fa7a2-ecac-4d8f-8cd1-36a127361d3d.jpg"]},{"attr":[{"type":"size","value":"32","id":"EG020103OJ3200"},{"type":"size","value":"34","id":"EG020103OJ3400"},{"type":"size","value":"36","id":"EG020103OJ3600"},{"type":"size","value":"38","id":"EG020103OJ3800"},{"type":"size","value":"40","id":"EG020103OJ4000"}],"cat":{"name":"Taager exclusive offers","text":"ุนุฑูุถ ุชุงุฌุฑ ุงูุญุตุฑูุฉ"},"id":"EG020103OJ3800","status":"available","desc":"ุฌุจูุงูู ุนุฑุถ ุงูุชูููุฑ 3๐ุ ุจูุทูููุงุช ุฌููุฒ ุจุงููุงู ุงุณุงุณูุฉ ูุงุฒู ุชููู ูู ุฏููุงุจูุ ููุงุณุจุฉ ู ูุงููุฉ ุนูู ูู ูุจุณู ุจุฎุงูุฉ ููุชุงุฒุฉ ู ุณุนุฑ ููุชุนูุถุด ุงูุญู ุงูุนุฑุถ ๐๐","title":"ูฃ ุฌููุฒ ุจูุฒูู","price":420,"specs":"โข *ุงูุชูุงุตูู*\r\nโข - ุงูููุฏูู : 3 ุฌููุฒ ุจูุฒูู \r\nโข - ุงูุฎุงูุฉ: ุฌููุฒ\r\nโข - ุงูููู: ( ุชูุฌู - ูุญูู - ูุญูู ูุงุชุญ )\r\nโข - ุงุฒุฑุงุฑ\r\nโข - (2 ุฌูุจ ุฃูุงููุ 2 ุฌูุจ ุฎููู)\r\nโข - ุงููุงู ุนูููุฉ ู ููุงุณุจุฉ\r\nโข *ููุงุณุงุช*\r\nโข - ููุงุณ 32 ููุจุณ ูู 55 - 65 ูููู\r\nโข ( ุทูู 106 ุณูุ ุนุฑุถ ุงููุณุท 40 ุณูุ ุทูู ุงูุญุฌุฑ 29 ุณูุ ุนุฑุถ ุงูุญุฌุฑ 50 ุณู)\r\nโข - ููุงุณ 34 ููุจุณ ูู 65 - 75 ูููู\r\nโข ( ุทูู 107 ุณูุ ุนุฑุถ ุงููุณุท 42 ุณูุ ุทูู ุงูุญุฌุฑ 29 ุณูุ ุนุฑุถ ุงูุญุฌุฑ 52 ุณู)\r\nโข - ููุงุณ 36 ููุจุณ ูู 75 - 85 ูููู\r\nโข ( ุทูู 108 ุณูุ ุนุฑุถ ุงููุณุท 44 ุณูุ ุทูู ุงูุญุฌุฑ 29 ุณูุ ุนุฑุถ ุงูุญุฌุฑ 54 ุณู)\r\nโข - ููุงุณ 38 ููุจุณ ูู 85 - 95 ูููู\r\nโข ( ุทูู 109 ุณูุ ุนุฑุถ ุงููุณุท 46 ุณูุ ุทูู ุงูุญุฌุฑ 29 ุณูุ ุนุฑุถ ุงูุญุฌุฑ 56 ุณู)\r\nโข - ููุงุณ 40 ููุจุณ ูู 95 - 100 ูููู\r\nโข ( ุทูู 110 ุณูุ ุนุฑุถ ุงููุณุท 48 ุณูุ ุทูู ุงูุญุฌุฑ 29 ุณูุ ุนุฑุถ ุงูุญุฌุฑ 58 ุณู)\r\nโข *ุงูุฎุงูุฉ ู ุงูุงุณุชุฎุฏุงู*\r\nโข - ุฌููุฒ/ ูููุฑุง\r\nโข - ูุนุงูุฌ ุถุฏ ุงูุงูููุงุด\r\nโข - ุงููุงู ุซุงุจุชุฉ\r\nโข - ูุงุจู ููุบุณู ูู ุงูุบุณุงูุฉ\r\nโข","hide":true,"media":["https://tager-uploads.s3.eu-central-1.amazonaws.com/ae25d4e5-4ac1-466b-a063-ea4f88f708b6.jpg","https://tager-uploads.s3.eu-central-1.amazonaws.com/19f44311-20b5-4a97-a02b-2db5b9375f56.jpg","https://tager-uploads.s3.eu-central-1.amazonaws.com/2e178509-6c8a-4201-b729-224f0943e379.jpg","https://tager-uploads.s3.eu-central-1.amazonaws.com/2b0904c5-fdd9-49dd-8f7e-036e0d959d9b.jpg","https://tager-uploads.s3.eu-central-1.amazonaws.com/aac11159-c13f-4f76-b3f8-2b3f4576bfa1.jpg","https://tager-uploads.s3.eu-central-1.amazonaws.com/4afbccfe-bf0e-43cc-ba01-8db171ac2961.jpg"]},{"attr":[{"type":"size","value":"32","id":"EG020103OJ3200"},{"type":"size","value":"34","id":"EG020103OJ3400"},{"type":"size","value":"36","id":"EG020103OJ3600"},{"type":"size","value":"38","id":"EG020103OJ3800"},{"type":"size","value":"40","id":"EG020103OJ4000"}],"cat":{"name":"Taager exclusive offers","text":"ุนุฑูุถ ุชุงุฌุฑ ุงูุญุตุฑูุฉ"},"id":"EG020103OJ4000","status":"available","desc":"ุฌุจูุงูู ุนุฑุถ ุงูุชูููุฑ 3๐ุ ุจูุทูููุงุช ุฌููุฒ ุจุงููุงู ุงุณุงุณูุฉ ูุงุฒู ุชููู ูู ุฏููุงุจูุ ููุงุณุจุฉ ู ูุงููุฉ ุนูู ูู ูุจุณู ุจุฎุงูุฉ ููุชุงุฒุฉ ู ุณุนุฑ ููุชุนูุถุด ุงูุญู ุงูุนุฑุถ ๐๐","title":"ูฃ ุฌููุฒ ุจูุฒูู","price":420,"specs":"โข *ุงูุชูุงุตูู*\r\nโข - ุงูููุฏูู : 3 ุฌููุฒ ุจูุฒูู \r\nโข - ุงูุฎุงูุฉ: ุฌููุฒ\r\nโข - ุงูููู: ( ุชูุฌู - ูุญูู - ูุญูู ูุงุชุญ )\r\nโข - ุงุฒุฑุงุฑ\r\nโข - (2 ุฌูุจ ุฃูุงููุ 2 ุฌูุจ ุฎููู)\r\nโข - ุงููุงู ุนูููุฉ ู ููุงุณุจุฉ\r\nโข *ููุงุณุงุช*\r\nโข - ููุงุณ 32 ููุจุณ ูู 55 - 65 ูููู\r\nโข ( ุทูู 106 ุณูุ ุนุฑุถ ุงููุณุท 40 ุณูุ ุทูู ุงูุญุฌุฑ 29 ุณูุ ุนุฑุถ ุงูุญุฌุฑ 50 ุณู)\r\nโข - ููุงุณ 34 ููุจุณ ูู 65 - 75 ูููู\r\nโข ( ุทูู 107 ุณูุ ุนุฑุถ ุงููุณุท 42 ุณูุ ุทูู ุงูุญุฌุฑ 29 ุณูุ ุนุฑุถ ุงูุญุฌุฑ 52 ุณู)\r\nโข - ููุงุณ 36 ููุจุณ ูู 75 - 85 ูููู\r\nโข ( ุทูู 108 ุณูุ ุนุฑุถ ุงููุณุท 44 ุณูุ ุทูู ุงูุญุฌุฑ 29 ุณูุ ุนุฑุถ ุงูุญุฌุฑ 54 ุณู)\r\nโข - ููุงุณ 38 ููุจุณ ูู 85 - 95 ูููู\r\nโข ( ุทูู 109 ุณูุ ุนุฑุถ ุงููุณุท 46 ุณูุ ุทูู ุงูุญุฌุฑ 29 ุณูุ ุนุฑุถ ุงูุญุฌุฑ 56 ุณู)\r\nโข - ููุงุณ 40 ููุจุณ ูู 95 - 100 ูููู\r\nโข ( ุทูู 110 ุณูุ ุนุฑุถ ุงููุณุท 48 ุณูุ ุทูู ุงูุญุฌุฑ 29 ุณูุ ุนุฑุถ ุงูุญุฌุฑ 58 ุณู)\r\nโข *ุงูุฎุงูุฉ ู ุงูุงุณุชุฎุฏุงู*\r\nโข - ุฌููุฒ/ ูููุฑุง\r\nโข - ูุนุงูุฌ ุถุฏ ุงูุงูููุงุด\r\nโข - ุงููุงู ุซุงุจุชุฉ\r\nโข - ูุงุจู ููุบุณู ูู ุงูุบุณุงูุฉ\r\nโข","hide":true,"media":["https://tager-uploads.s3.eu-central-1.amazonaws.com/108f0703-3c36-49f1-923e-0cca57697caf.jpg","https://tager-uploads.s3.eu-central-1.amazonaws.com/7cf035e1-5b05-4d85-9b58-568a0124a66f.jpg","https://tager-uploads.s3.eu-central-1.amazonaws.com/fac3d542-9b86-4bc2-bf68-aa64512c40f0.jpg","https://tager-uploads.s3.eu-central-1.amazonaws.com/56a5003a-3e1b-4adf-9041-2752d8a41c4b.jpg","https://tager-uploads.s3.eu-central-1.amazonaws.com/41cc5651-309f-48d0-8b41-bb73ec4b26ef.jpg","https://tager-uploads.s3.eu-central-1.amazonaws.com/9482135d-7f91-4b06-b0ce-972bf178df8b.jpg"]},{"attr":[{"type":"size","value":"32","id":"EG020103CJ3200"},{"type":"size","value":"34","id":"EG020103CJ3400"},{"type":"size","value":"36","id":"EG020103CJ3600"},{"type":"size","value":"38","id":"EG020103CJ3800"},{"type":"size","value":"40","id":"EG020103CJ4000"}],"cat":{"name":"Taager exclusive offers","text":"ุนุฑูุถ ุชุงุฌุฑ ุงูุญุตุฑูุฉ"},"id":"EG020103CJ3200","status":"available","desc":"ุนุดุงู ุนุงุฑููู ุงู ุงูุจูุทููู ุงูุฌููุฒ ูุทุนุฉ ุงุณุงุณูุฉ ููููุฉ ูู ุฏููุงุจูุ ููุฑูุงูู ุนุฑุถ ูฃ ุฌููุฒ ูุงุฌูุงู ุชูุฏุฑ ุชุจุฏู ูููู ููู ุฎุฑูุฌุงุชูุ ุนุฑุถ ุจูููุฑูู ุณุนุฑ 3 ุจูุงุทูู ุจูุตู ุงูุซูู๐","title":"ูฃ ุฌููุฒ ูุงุฌูุงู","price":420,"specs":"โข *ุงูุชูุงุตูู*\r\nโข - ุงูููุฏูู : ูฃ ุฌููุฒ ูุงุฌูุงู \r\nโข - ุงูุฎุงูุฉ: ุฌููุฒ\r\nโข - ุงูููู: ( ุชูุฌู - ูุญูู - ูุญูู ูุงุชุญ )\r\nโข - ุงุฒุฑุงุฑ\r\nโข - (2 ุฌูุจ ุฃูุงููุ 2 ุฌูุจ ุฎููู)\r\nโข - ุงููุงู ุนูููุฉ ู ููุงุณุจุฉ\r\nโข *ููุงุณุงุช*\r\nโข - ููุงุณ 32 ููุจุณ ูู 55 - 65 ูููู\r\nโข ( ุทูู 106 ุณูุ ุนุฑุถ ุงููุณุท 40 ุณูุ ุทูู ุงูุญุฌุฑ 29 ุณูุ ุนุฑุถ ุงูุญุฌุฑ 50 ุณู)\r\nโข - ููุงุณ 34 ููุจุณ ูู 65 - 75 ูููู\r\nโข ( ุทูู 107 ุณูุ ุนุฑุถ ุงููุณุท 42 ุณูุ ุทูู ุงูุญุฌุฑ 29 ุณูุ ุนุฑุถ ุงูุญุฌุฑ 52 ุณู)\r\nโข - ููุงุณ 36 ููุจุณ ูู 75 - 85 ูููู\r\nโข ( ุทูู 108 ุณูุ ุนุฑุถ ุงููุณุท 44 ุณูุ ุทูู ุงูุญุฌุฑ 29 ุณูุ ุนุฑุถ ุงูุญุฌุฑ 54 ุณู)\r\nโข - ููุงุณ 38 ููุจุณ ูู 85 - 95 ูููู\r\nโข ( ุทูู 109 ุณูุ ุนุฑุถ ุงููุณุท 46 ุณูุ ุทูู ุงูุญุฌุฑ 29 ุณูุ ุนุฑุถ ุงูุญุฌุฑ 56 ุณู)\r\nโข - ููุงุณ 40 ููุจุณ ูู 95 - 100 ูููู\r\nโข ( ุทูู 110 ุณูุ ุนุฑุถ ุงููุณุท 48 ุณูุ ุทูู ุงูุญุฌุฑ 29 ุณูุ ุนุฑุถ ุงูุญุฌุฑ 58 ุณู)\r\nโข *ุงูุฎุงูุฉ ู ุงูุงุณุชุฎุฏุงู*\r\nโข - ุฌููุฒ/ ูููุฑุง\r\nโข - ูุนุงูุฌ ุถุฏ ุงูุงูููุงุด\r\nโข - ุงููุงู ุซุงุจุชุฉ\r\nโข - ูุงุจู ููุบุณู ูู ุงูุบุณุงูุฉ\r\nโข","media":["https://tager-uploads.s3.eu-central-1.amazonaws.com/8fc90b03-b6ba-4306-bebc-ee9bb40cd9bc.jpg","https://tager-uploads.s3.eu-central-1.amazonaws.com/3fdec3ef-93c1-4829-9b7d-7093dd7b75a2.jpg","https://tager-uploads.s3.eu-central-1.amazonaws.com/120f8671-7738-47ff-990f-8b8dfc646402.jpg","https://tager-uploads.s3.eu-central-1.amazonaws.com/5d40820b-4116-4ee8-8872-dbe6882a1ad6.jpg","https://tager-uploads.s3.eu-central-1.amazonaws.com/05bfc1e5-a409-4b69-bd7b-03f13393794d.jpg","https://tager-uploads.s3.eu-central-1.amazonaws.com/589f750d-cddc-4a3e-a3ae-c6b42cd9ef39.jpg"]},{"attr":[{"type":"size","value":"32","id":"EG020103CJ3200"},{"type":"size","value":"34","id":"EG020103CJ3400"},{"type":"size","value":"36","id":"EG020103CJ3600"},{"type":"size","value":"38","id":"EG020103CJ3800"},{"type":"size","value":"40","id":"EG020103CJ4000"}],"cat":{"name":"Taager exclusive offers","text":"ุนุฑูุถ ุชุงุฌุฑ ุงูุญุตุฑูุฉ"},"id":"EG020103CJ3400","status":"available","desc":"ุนุดุงู ุนุงุฑููู ุงู ุงูุจูุทููู ุงูุฌููุฒ ูุทุนุฉ ุงุณุงุณูุฉ ููููุฉ ูู ุฏููุงุจูุ ููุฑูุงูู ุนุฑุถ ูฃ ุฌููุฒ ูุงุฌูุงู ุชูุฏุฑ ุชุจุฏู ูููู ููู ุฎุฑูุฌุงุชูุ ุนุฑุถ ุจูููุฑูู ุณุนุฑ 3 ุจูุงุทูู ุจูุตู ุงูุซูู๐","title":"ูฃ ุฌููุฒ ูุงุฌูุงู","price":420,"specs":"โข *ุงูุชูุงุตูู*\r\nโข - ุงูููุฏูู : ูฃ ุฌููุฒ ูุงุฌูุงู \r\nโข - ุงูุฎุงูุฉ: ุฌููุฒ\r\nโข - ุงูููู: ( ุชูุฌู - ูุญูู - ูุญูู ูุงุชุญ )\r\nโข - ุงุฒุฑุงุฑ\r\nโข - (2 ุฌูุจ ุฃูุงููุ 2 ุฌูุจ ุฎููู)\r\nโข - ุงููุงู ุนูููุฉ ู ููุงุณุจุฉ\r\nโข *ููุงุณุงุช*\r\nโข - ููุงุณ 32 ููุจุณ ูู 55 - 65 ูููู\r\nโข ( ุทูู 106 ุณูุ ุนุฑุถ ุงููุณุท 40 ุณูุ ุทูู ุงูุญุฌุฑ 29 ุณูุ ุนุฑุถ ุงูุญุฌุฑ 50 ุณู)\r\nโข - ููุงุณ 34 ููุจุณ ูู 65 - 75 ูููู\r\nโข ( ุทูู 107 ุณูุ ุนุฑุถ ุงููุณุท 42 ุณูุ ุทูู ุงูุญุฌุฑ 29 ุณูุ ุนุฑุถ ุงูุญุฌุฑ 52 ุณู)\r\nโข - ููุงุณ 36 ููุจุณ ูู 75 - 85 ูููู\r\nโข ( ุทูู 108 ุณูุ ุนุฑุถ ุงููุณุท 44 ุณูุ ุทูู ุงูุญุฌุฑ 29 ุณูุ ุนุฑุถ ุงูุญุฌุฑ 54 ุณู)\r\nโข - ููุงุณ 38 ููุจุณ ูู 85 - 95 ูููู\r\nโข ( ุทูู 109 ุณูุ ุนุฑุถ ุงููุณุท 46 ุณูุ ุทูู ุงูุญุฌุฑ 29 ุณูุ ุนุฑุถ ุงูุญุฌุฑ 56 ุณู)\r\nโข - ููุงุณ 40 ููุจุณ ูู 95 - 100 ูููู\r\nโข ( ุทูู 110 ุณูุ ุนุฑุถ ุงููุณุท 48 ุณูุ ุทูู ุงูุญุฌุฑ 29 ุณูุ ุนุฑุถ ุงูุญุฌุฑ 58 ุณู)\r\nโข *ุงูุฎุงูุฉ ู ุงูุงุณุชุฎุฏุงู*\r\nโข - ุฌููุฒ/ ูููุฑุง\r\nโข - ูุนุงูุฌ ุถุฏ ุงูุงูููุงุด\r\nโข - ุงููุงู ุซุงุจุชุฉ\r\nโข - ูุงุจู ููุบุณู ูู ุงูุบุณุงูุฉ\r\nโข","hide":true,"media":["https://tager-uploads.s3.eu-central-1.amazonaws.com/00e0043e-6ac3-471f-b861-9300c8eeab79.jpg","https://tager-uploads.s3.eu-central-1.amazonaws.com/ca54a95a-f8fd-4df6-82dd-7b066e073316.jpg","https://tager-uploads.s3.eu-central-1.amazonaws.com/56539e0a-536c-42e2-abbb-8b0190a05e48.jpg","https://tager-uploads.s3.eu-central-1.amazonaws.com/92650eea-2556-42a8-b3cb-0e356ccb1c3a.jpg","https://tager-uploads.s3.eu-central-1.amazonaws.com/9fc9d816-69c0-4683-b753-ae892ac4c915.jpg","https://tager-uploads.s3.eu-central-1.amazonaws.com/77e2d722-c6d5-43d4-987c-64050c38f7be.jpg"]},{"attr":[{"type":"size","value":"32","id":"EG020103CJ3200"},{"type":"size","value":"34","id":"EG020103CJ3400"},{"type":"size","value":"36","id":"EG020103CJ3600"},{"type":"size","value":"38","id":"EG020103CJ3800"},{"type":"size","value":"40","id":"EG020103CJ4000"}],"cat":{"name":"Taager exclusive offers","text":"ุนุฑูุถ ุชุงุฌุฑ ุงูุญุตุฑูุฉ"},"id":"EG020103CJ3600","status":"available","desc":"ุนุดุงู ุนุงุฑููู ุงู ุงูุจูุทููู ุงูุฌููุฒ ูุทุนุฉ ุงุณุงุณูุฉ ููููุฉ ูู ุฏููุงุจูุ ููุฑูุงูู ุนุฑุถ ูฃ ุฌููุฒ ูุงุฌูุงู ุชูุฏุฑ ุชุจุฏู ูููู ููู ุฎุฑูุฌุงุชูุ ุนุฑุถ ุจูููุฑูู ุณุนุฑ 3 ุจูุงุทูู ุจูุตู ุงูุซูู๐","title":"ูฃ ุฌููุฒ ูุงุฌูุงู","price":420,"specs":"โข *ุงูุชูุงุตูู*\r\nโข - ุงูููุฏูู : ูฃ ุฌููุฒ ูุงุฌูุงู \r\nโข - ุงูุฎุงูุฉ: ุฌููุฒ\r\nโข - ุงูููู: ( ุชูุฌู - ูุญูู - ูุญูู ูุงุชุญ )\r\nโข - ุงุฒุฑุงุฑ\r\nโข - (2 ุฌูุจ ุฃูุงููุ 2 ุฌูุจ ุฎููู)\r\nโข - ุงููุงู ุนูููุฉ ู ููุงุณุจุฉ\r\nโข *ููุงุณุงุช*\r\nโข - ููุงุณ 32 ููุจุณ ูู 55 - 65 ูููู\r\nโข ( ุทูู 106 ุณูุ ุนุฑุถ ุงููุณุท 40 ุณูุ ุทูู ุงูุญุฌุฑ 29 ุณูุ ุนุฑุถ ุงูุญุฌุฑ 50 ุณู)\r\nโข - ููุงุณ 34 ููุจุณ ูู 65 - 75 ูููู\r\nโข ( ุทูู 107 ุณูุ ุนุฑุถ ุงููุณุท 42 ุณูุ ุทูู ุงูุญุฌุฑ 29 ุณูุ ุนุฑุถ ุงูุญุฌุฑ 52 ุณู)\r\nโข - ููุงุณ 36 ููุจุณ ูู 75 - 85 ูููู\r\nโข ( ุทูู 108 ุณูุ ุนุฑุถ ุงููุณุท 44 ุณูุ ุทูู ุงูุญุฌุฑ 29 ุณูุ ุนุฑุถ ุงูุญุฌุฑ 54 ุณู)\r\nโข - ููุงุณ 38 ููุจุณ ูู 85 - 95 ูููู\r\nโข ( ุทูู 109 ุณูุ ุนุฑุถ ุงููุณุท 46 ุณูุ ุทูู ุงูุญุฌุฑ 29 ุณูุ ุนุฑุถ ุงูุญุฌุฑ 56 ุณู)\r\nโข - ููุงุณ 40 ููุจุณ ูู 95 - 100 ูููู\r\nโข ( ุทูู 110 ุณูุ ุนุฑุถ ุงููุณุท 48 ุณูุ ุทูู ุงูุญุฌุฑ 29 ุณูุ ุนุฑุถ ุงูุญุฌุฑ 58 ุณู)\r\nโข *ุงูุฎุงูุฉ ู ุงูุงุณุชุฎุฏุงู*\r\nโข - ุฌููุฒ/ ูููุฑุง\r\nโข - ูุนุงูุฌ ุถุฏ ุงูุงูููุงุด\r\nโข - ุงููุงู ุซุงุจุชุฉ\r\nโข - ูุงุจู ููุบุณู ูู ุงูุบุณุงูุฉ\r\nโข","hide":true,"media":["https://tager-uploads.s3.eu-central-1.amazonaws.com/862665be-5844-47f8-9a8b-bab5000dc392.jpg","https://tager-uploads.s3.eu-central-1.amazonaws.com/e5caa2b4-a879-4822-8762-9c504c884388.jpg","https://tager-uploads.s3.eu-central-1.amazonaws.com/27b4ddb1-69f4-4c63-b8cb-d0cccdb8a208.jpg","https://tager-uploads.s3.eu-central-1.amazonaws.com/65258727-ce54-439d-82dd-074acf0ebe6d.jpg","https://tager-uploads.s3.eu-central-1.amazonaws.com/5888d994-ab3f-4767-a87e-7be1b041c7d4.jpg","https://tager-uploads.s3.eu-central-1.amazonaws.com/ac787f38-403a-4da5-8421-0222a7cc3f9e.jpg"]},{"attr":[{"type":"size","value":"32","id":"EG020103CJ3200"},{"type":"size","value":"34","id":"EG020103CJ3400"},{"type":"size","value":"36","id":"EG020103CJ3600"},{"type":"size","value":"38","id":"EG020103CJ3800"},{"type":"size","value":"40","id":"EG020103CJ4000"}],"cat":{"name":"Taager exclusive offers","text":"ุนุฑูุถ ุชุงุฌุฑ ุงูุญุตุฑูุฉ"},"id":"EG020103CJ3800","status":"available","desc":"ุนุดุงู ุนุงุฑููู ุงู ุงูุจูุทููู ุงูุฌููุฒ ูุทุนุฉ ุงุณุงุณูุฉ ููููุฉ ูู ุฏููุงุจูุ ููุฑูุงูู ุนุฑุถ ูฃ ุฌููุฒ ูุงุฌูุงู ุชูุฏุฑ ุชุจุฏู ูููู ููู ุฎุฑูุฌุงุชูุ ุนุฑุถ ุจูููุฑูู ุณุนุฑ 3 ุจูุงุทูู ุจูุตู ุงูุซูู๐","title":"ูฃ ุฌููุฒ ูุงุฌูุงู","price":420,"specs":"โข *ุงูุชูุงุตูู*\r\nโข - ุงูููุฏูู : ูฃ ุฌููุฒ ูุงุฌูุงู \r\nโข - ุงูุฎุงูุฉ: ุฌููุฒ\r\nโข - ุงูููู: ( ุชูุฌู - ูุญูู - ูุญูู ูุงุชุญ )\r\nโข - ุงุฒุฑุงุฑ\r\nโข - (2 ุฌูุจ ุฃูุงููุ 2 ุฌูุจ ุฎููู)\r\nโข - ุงููุงู ุนูููุฉ ู ููุงุณุจุฉ\r\nโข *ููุงุณุงุช*\r\nโข - ููุงุณ 32 ููุจุณ ูู 55 - 65 ูููู\r\nโข ( ุทูู 106 ุณูุ ุนุฑุถ ุงููุณุท 40 ุณูุ ุทูู ุงูุญุฌุฑ 29 ุณูุ ุนุฑุถ ุงูุญุฌุฑ 50 ุณู)\r\nโข - ููุงุณ 34 ููุจุณ ูู 65 - 75 ูููู\r\nโข ( ุทูู 107 ุณูุ ุนุฑุถ ุงููุณุท 42 ุณูุ ุทูู ุงูุญุฌุฑ 29 ุณูุ ุนุฑุถ ุงูุญุฌุฑ 52 ุณู)\r\nโข - ููุงุณ 36 ููุจุณ ูู 75 - 85 ูููู\r\nโข ( ุทูู 108 ุณูุ ุนุฑุถ ุงููุณุท 44 ุณูุ ุทูู ุงูุญุฌุฑ 29 ุณูุ ุนุฑุถ ุงูุญุฌุฑ 54 ุณู)\r\nโข - ููุงุณ 38 ููุจุณ ูู 85 - 95 ูููู\r\nโข ( ุทูู 109 ุณูุ ุนุฑุถ ุงููุณุท 46 ุณูุ ุทูู ุงูุญุฌุฑ 29 ุณูุ ุนุฑุถ ุงูุญุฌุฑ 56 ุณู)\r\nโข - ููุงุณ 40 ููุจุณ ูู 95 - 100 ูููู\r\nโข ( ุทูู 110 ุณูุ ุนุฑุถ ุงููุณุท 48 ุณูุ ุทูู ุงูุญุฌุฑ 29 ุณูุ ุนุฑุถ ุงูุญุฌุฑ 58 ุณู)\r\nโข *ุงูุฎุงูุฉ ู ุงูุงุณุชุฎุฏุงู*\r\nโข - ุฌููุฒ/ ูููุฑุง\r\nโข - ูุนุงูุฌ ุถุฏ ุงูุงูููุงุด\r\nโข - ุงููุงู ุซุงุจุชุฉ\r\nโข - ูุงุจู ููุบุณู ูู ุงูุบุณุงูุฉ\r\nโข","hide":true,"media":["https://tager-uploads.s3.eu-central-1.amazonaws.com/ea0a8ec4-102c-4d3c-94ce-63aaeb3c5973.jpg","https://tager-uploads.s3.eu-central-1.amazonaws.com/4963d03f-ddd9-4a3a-93f7-4bd8b4822835.jpg","https://tager-uploads.s3.eu-central-1.amazonaws.com/d152a060-36d9-4aa2-ad41-3b41d77ed9e7.jpg","https://tager-uploads.s3.eu-central-1.amazonaws.com/9e076ef3-b595-4090-b7d8-d17b40b2dae2.jpg","https://tager-uploads.s3.eu-central-1.amazonaws.com/a69d4dca-0a05-42a6-9779-637fae1e3d37.jpg","https://tager-uploads.s3.eu-central-1.amazonaws.com/41b3d009-0529-41d3-bc90-1f0cadcbc380.jpg"]},{"attr":[{"type":"size","value":"32","id":"EG020103CJ3200"},{"type":"size","value":"34","id":"EG020103CJ3400"},{"type":"size","value":"36","id":"EG020103CJ3600"},{"type":"size","value":"38","id":"EG020103CJ3800"},{"type":"size","value":"40","id":"EG020103CJ4000"}],"cat":{"name":"Taager exclusive offers","text":"ุนุฑูุถ ุชุงุฌุฑ ุงูุญุตุฑูุฉ"},"id":"EG020103CJ4000","status":"available","desc":"ุนุดุงู ุนุงุฑููู ุงู ุงูุจูุทููู ุงูุฌููุฒ ูุทุนุฉ ุงุณุงุณูุฉ ููููุฉ ูู ุฏููุงุจูุ ููุฑูุงูู ุนุฑุถ ูฃ ุฌููุฒ ูุงุฌูุงู ุชูุฏุฑ ุชุจุฏู ูููู ููู ุฎุฑูุฌุงุชูุ ุนุฑุถ ุจูููุฑูู ุณุนุฑ 3 ุจูุงุทูู ุจูุตู ุงูุซูู๐","title":"ูฃ ุฌููุฒ ูุงุฌูุงู","price":420,"specs":"โข *ุงูุชูุงุตูู*\r\nโข - ุงูููุฏูู : ูฃ ุฌููุฒ ูุงุฌูุงู \r\nโข - ุงูุฎุงูุฉ: ุฌููุฒ\r\nโข - ุงูููู: ( ุชูุฌู - ูุญูู - ูุญูู ูุงุชุญ )\r\nโข - ุงุฒุฑุงุฑ\r\nโข - (2 ุฌูุจ ุฃูุงููุ 2 ุฌูุจ ุฎููู)\r\nโข - ุงููุงู ุนูููุฉ ู ููุงุณุจุฉ\r\nโข *ููุงุณุงุช*\r\nโข - ููุงุณ 32 ููุจุณ ูู 55 - 65 ูููู\r\nโข ( ุทูู 106 ุณูุ ุนุฑุถ ุงููุณุท 40 ุณูุ ุทูู ุงูุญุฌุฑ 29 ุณูุ ุนุฑุถ ุงูุญุฌุฑ 50 ุณู)\r\nโข - ููุงุณ 34 ููุจุณ ูู 65 - 75 ูููู\r\nโข ( ุทูู 107 ุณูุ ุนุฑุถ ุงููุณุท 42 ุณูุ ุทูู ุงูุญุฌุฑ 29 ุณูุ ุนุฑุถ ุงูุญุฌุฑ 52 ุณู)\r\nโข - ููุงุณ 36 ููุจุณ ูู 75 - 85 ูููู\r\nโข ( ุทูู 108 ุณูุ ุนุฑุถ ุงููุณุท 44 ุณูุ ุทูู ุงูุญุฌุฑ 29 ุณูุ ุนุฑุถ ุงูุญุฌุฑ 54 ุณู)\r\nโข - ููุงุณ 38 ููุจุณ ูู 85 - 95 ูููู\r\nโข ( ุทูู 109 ุณูุ ุนุฑุถ ุงููุณุท 46 ุณูุ ุทูู ุงูุญุฌุฑ 29 ุณูุ ุนุฑุถ ุงูุญุฌุฑ 56 ุณู)\r\nโข - ููุงุณ 40 ููุจุณ ูู 95 - 100 ูููู\r\nโข ( ุทูู 110 ุณูุ ุนุฑุถ ุงููุณุท 48 ุณูุ ุทูู ุงูุญุฌุฑ 29 ุณูุ ุนุฑุถ ุงูุญุฌุฑ 58 ุณู)\r\nโข *ุงูุฎุงูุฉ ู ุงูุงุณุชุฎุฏุงู*\r\nโข - ุฌููุฒ/ ูููุฑุง\r\nโข - ูุนุงูุฌ ุถุฏ ุงูุงูููุงุด\r\nโข - ุงููุงู ุซุงุจุชุฉ\r\nโข - ูุงุจู ููุบุณู ูู ุงูุบุณุงูุฉ\r\nโข","hide":true,"media":["https://tager-uploads.s3.eu-central-1.amazonaws.com/12a0adc6-8d07-434c-aa37-a5004e3b1bd7.jpg","https://tager-uploads.s3.eu-central-1.amazonaws.com/fa05d2be-a5a0-4c66-a363-278f8f17ecc8.jpg","https://tager-uploads.s3.eu-central-1.amazonaws.com/20c69d85-9b7d-48f0-8cad-75fcb308143c.jpg","https://tager-uploads.s3.eu-central-1.amazonaws.com/80e42061-ab61-422c-b993-ada566d040e2.jpg","https://tager-uploads.s3.eu-central-1.amazonaws.com/73dc4129-ecc7-492c-9bb9-63c1089dbc37.jpg","https://tager-uploads.s3.eu-central-1.amazonaws.com/63fbed7a-244a-4da7-9f65-e8f956ae4f31.jpg"]},{"cat":{"name":"Taager exclusive offers","text":"ุนุฑูุถ ุชุงุฌุฑ ุงูุญุตุฑูุฉ"},"id":"EG0305013FHM99","status":"available","desc":"ูุชููู ูู ููุงู ุงูุญูููุงุช ุงูููุฌูุฏุฉ ูู ุงูุจูุช ู ูุชููุฑู ูููุณ ุงูููุงุชุฑ ุงูุบุงููุฉ ูุน ุนุฑุถ ุซูุงุซ ูุทุน ููุชุฑ ุญูููุฉ 5 ูุฑุงุญู","title":"ุนุฑุถ ุซูุงุซ ูุทุน ููุชุฑ ุญูููุฉ 5 ูุฑุงุญู","price":100,"specs":"โข ุงููููุฒุงุช\r\nโข ุตุบูุฑุฉ ุจุฃุจุนุงุฏ 7 *4*2 ุณู ุชูุฑูุจูุง ูุนูู ูุด ูุชุงุฎุฏ ููุงู ูู ุญูุถ ุงููุทุจุฎ\r\nโข ุงูููุชุฑ ููู ุฃููุดุฉ PVA ุบูุฑ ููุณูุฌุฉ ุตุญูุฉ ุจุชูุฒู ุงูููุฉ ู ุชุญุฌุฒ ูู ุงูุญุตู ู ุงูุฑูู\r\nโข ููุงู ุงูููุฉ ุจุนุฏ ุงูุชูููุฉ ุจุชุนุฏู ุนูู ูุจุฑูุช ุงููุงูุณููู ูุงููุฑุจูู ุงูููุดุท ุจุงูุฌูุฒ ุงูููุฏ ุจูุฒูุฏู ุงูููุฉ ููุงุก ูุชููู ุตุญูุฉ ุฃูุชุฑ\r\nโข ูุตููุน ูู ุงูุจูุงุณุชูู ุงูุตุญู ุงููุชูู ุงููู ูุณุชุญูู ููุฉ ุถุบุท ุงูููุงู\r\nโข ุงููุตู\r\nโข ุงูุฃุจุนุงุฏ: 7*4*2 ุณู ุชูุฑูุจูุง\r\nโข ุงูุฎุงูุฉ: ุจูุงุณุชูู ุตุญู\r\nโข ูุญุชูู ุงูุนุจูุฉ\r\nโข 3รููุชุฑ ุญูููุฉ .","media":["https://tager-uploads.s3.eu-central-1.amazonaws.com/93affa35-09a4-45b4-a600-6a6d05b12bbf.jpg","https://tager-uploads.s3.eu-central-1.amazonaws.com/995a26b9-925e-4ff9-bf7a-671855a4ace3.jpg","https://tager-uploads.s3.eu-central-1.amazonaws.com/477b59b3-cd6c-49ac-8d8d-8f7541617ceb.jpg","https://tager-uploads.s3.eu-central-1.amazonaws.com/20922581-e5d6-4422-9541-5ce954c3046a.jpg","https://tager-uploads.s3.eu-central-1.amazonaws.com/f1f7bfd5-a4a8-4795-9731-08f5239004e8.jpg"]},{"cat":{"name":"Taager exclusive offers","text":"ุนุฑูุถ ุชุงุฌุฑ ุงูุญุตุฑูุฉ"},"id":"EG050701PN0099","status":"available","desc":"ุฃููุฐ ุนุฑุจูุชู ูู ุฃู ุถุฑุฑ ูุญุตููุง ูุน ุนุฑุถ  (ุงุฏุงุฉ ุงุตูุงุญ ูุงุณุชุนุฏุงู ุตุฏูุงุช ุงูุณูุงุฑุฉ +ูุนุฌูู ุฎุฏูุด ุงูุณูุงุฑุงุช) ูุชุฑุฌุน ุนุฑุจูุชู ุฒู ูุง ูุงูุช ูู ุบูุฑ ุฎุฏุด ุจุฃูู ุงูุชูุงููู.","title":"ุนุฑุถ (ุงุฏุงุฉ ูุงุตูุงุญ ู ุงุณุชุนุฏุงู ุตุฏูุงุช ุงูุณูุงุฑุฉ ุจููุณู APT +ูุนุฌูู ุฎุฏูุด ุงูุณูุงุฑุงุช)","price":210,"specs":"โข *ูููุฒุงุช ุงุฏุงุฉ ูุงุตูุงุญ ู ุงุณุชุนุฏุงู ุตุฏูุงุช*\r\nโข ูุชูุฏุฑ ุชุฑุฏ ุงูุฎุจุทุงุช ูุงูุตุฏูุงุช ุจููุณู ุจุณูููุฉ\r\nโข ูุชูู ููุชุญูู ูููุง ูุงูุช ุงูุฎุจุทุฉ\r\nโข ุญุฌูู ุตุบูุฑ ูุด ููุงุฎุฏ ูุณุงุญุฉ ูู ุนุฑุจูุชู\r\nโข ููููุฑ ุนููู ุงูููุช ูุงููุฌููุฏ ุงููู ุจูุถูุน ุนูุฏ ุงูุณููุฑู\r\nโข ุงููุตู\r\nโข ุงุฏุงุฉ ุงุตูุงุญ ุงูุตุฏูุงุช ุจููุณู\r\nโข ูุงุฑูุฉ: APT\r\nโข ุงูุงุจุนุงุฏ:(13*14)\r\nโข *ูููุฒุงุช ูุนุฌูู ุฎุฏูุด ุงูุณูุงุฑุงุช*\r\nโข ุงููุนุฌูู ูุฎูุตู ูู ูู ุงูุฎุฏูุด ูู ุนุฑุจูุชู ุจุณูููุฉ\r\nโข ููุฎูุตู ูู ุงูุฎุฏูุด ุงูุนูููุฉุ ุงูุณุทุญูุฉ ูุงูุบูุฑ ุทุจูุนูุฉ\r\nโข ุงููุนุฌูู ููุฎูุตู ูู ุงุซุงุฑ ุญุฑูู ุงูุดูุณ ุงููู ุจุชุฃุซุฑ ุนูู ููู ุงูุนุฑุจูุฉ\r\nโข ุงููุฒูู ุณูู ุงูุงุณุชุฎุฏุงู ูู ุฏูุงุฆู ุงูุนุฑุจูุฉ ูุชุฑุฌุน ุฌุฏูุฏุฉ\r\nโข ููุงุณุจ ููู ุงููุงุน ุงูุณูุงุฑุชุ ุงูููุชูุณูููุงุชุ ุงูุจูุงุฎุฑ ููู ุงููุงุน ุงููุฑูุจุงุช\r\nโข ูุนุงู ุงุณููุฌู ุนุดุงู ุชุณูู ุนููู ุงูุงุณุชุฎุฏุงู\r\nโข ุงููุตู\r\nโข ูุนุฌูู ูุฒูู ุงูุฎุฏูุด ููุณูุงุฑุงุช\r\nโข ูุญุชูู ุงูุนุจูุฉ\r\nโข ุงููุนุฌูู\r\nโข ุงุณููุฌู\r\nโข \"ุงูุญุฌู: 15 ูู\r\nโข","media":["https://tager-uploads.s3.eu-central-1.amazonaws.com/02c04fba-80a9-40a1-aa09-70762079bc80.jpg","https://tager-uploads.s3.eu-central-1.amazonaws.com/59b36f8d-c5b6-4643-b820-689c5b922439.jpg","https://tager-uploads.s3.eu-central-1.amazonaws.com/c772d5f4-67fc-4169-bcbd-72b6f7e714c0.jpg","https://tager-uploads.s3.eu-central-1.amazonaws.com/bdd62c8a-98f1-41e5-8f3f-ed5570145c6b.jpg","https://tager-uploads.s3.eu-central-1.amazonaws.com/6697d016-4db1-4412-9ea4-e7a580ee6fcb.jpg","https://tager-uploads.s3.eu-central-1.amazonaws.com/af162b10-5c41-4aa5-878b-ce681f060f51.jpg"]},{"cat":{"name":"Taager exclusive offers","text":"ุนุฑูุถ ุชุงุฌุฑ ุงูุญุตุฑูุฉ"},"id":"EG030501DIMA99","status":"available","desc":"ูู ุงูุทุนุงู ุงููุฌูุฏ ูุด ููุจูู ูุดููุฉ ูู ุฏูุงูู ูุชุชุฎูุตู ูู ูู ุงูุชูุฌ ูุน ุนุฑุถ ูุทุนุชูู ุทุจู ุณุญุฑู ูุงุฐุงุจุฉ ุชุฌููุฏ ุงูุทุนุงู .","title":"ุนุฑุถ ูุทุนุชูู ุทุจู ุณุญุฑู ูุฅุฐุงุจุฉ ุชุฌููุฏ ุงูุทุนุงู Defrost Express","price":200,"specs":"โข *ุงููููุฒุงุช*\r\nโข ูุชููุฑู ููุช ู ููุงู ููุฑุจุงุก .\r\nโข ูุชููู ุงูุชูุฌ ุนู ูู ุงููุฌูุฏุงุช ุฎุถุฑุงูุงุช ููุงููุฉ ูุด ูุญูู ุจุณ .\r\nโข ุณููุฉ ุงูุงุณุชุฎุฏุงู ูุณุฑูุนุฉ ุงูุชูุถูู ู ุขููุฉ ุฌุฏุง ุนูู ุบุณุงูุฉ ุงูุงุทุจุงู .\r\nโข *ุงููุตู*\r\nโข ุงูุงุจุนุงุฏ :- 21ร29 ุณู .\r\nโข *ูุญุชูู ุงูุนุจูุฉ*\r\nโข 2รุทุจู ุณุญุฑู ูุงุฐุงุจุฉ ุชุฌููุฏ ุงูุทุนุงู .\r\nโข","media":["https://tager-uploads.s3.eu-central-1.amazonaws.com/afded988-1c44-41ed-92f2-34444442df84.jpg","https://tager-uploads.s3.eu-central-1.amazonaws.com/f6304592-bd51-4c36-8976-166bea271178.jpg","https://tager-uploads.s3.eu-central-1.amazonaws.com/c0cef89a-5579-4acc-ac14-d2cfb87943fb.jpg","https://tager-uploads.s3.eu-central-1.amazonaws.com/df81b484-9b63-4011-b962-d196cb63fe07.jpg","https://tager-uploads.s3.eu-central-1.amazonaws.com/3f6b9349-8bf8-43af-943d-28699abc92b2.jpg"]},{"cat":{"name":"Taager exclusive offers","text":"ุนุฑูุถ ุชุงุฌุฑ ุงูุญุตุฑูุฉ"},"id":"EG030501DIST99","status":"available","desc":"ููุฑูุงูู ูู ุงูููุชุฌุงุช ุงูู ูุชุณุชุฎุฏูููุง ุนุดุงู ุชุนููู ุงูุงูู ุจูู ุณูููุฉ ู ูู ุงุณุฑ ููุช ูุน ุนุฑุถ ุทุจู ุณุญุฑู ูุงุฐุงุจุฉ ุชุฌููุฏ ุงูุทุนุงู +ุดูุงูุฉ ุจูุชุฌุงุฒ .","title":"\" ุนุฑุถ ุทุจู ุณุญุฑู ูุฅุฐุงุจุฉ ุชุฌููุฏ ุงูุทุนุงู Defrost Express +ุดูุงูุฉ ุจูุชุฌุงุฒ STAR MAX\"","price":300,"specs":"โข *ุงููููุฒุงุช*\r\nโข ูููุฒุงุช ุทุจู ุณุญุฑู ูุงุฐุงุจุฉ ุงูุชูุฌ \r\nโข ูุชููุฑู ููุช ู ููุงู ููุฑุจุงุก .\r\nโข ูุชููู ุงูุชูุฌ ุนู ูู ุงููุฌูุฏุงุช ุฎุถุฑุงูุงุช ููุงููุฉ ูุด ูุญูู ุจุณ .\r\nโข ุณููุฉ ุงูุงุณุชุฎุฏุงู ูุณุฑูุนุฉ ุงูุชูุถูู ู ุขููุฉ ุฌุฏุง ุนูู ุบุณุงูุฉ ุงูุงุทุจุงู .\r\nโข ูููุฒุงุช ุดูุงูุฉ ุจูุชุฌุงุฒ star max\r\nโข ูุด ุจุชุทูุน ุฏุฎุงู ุชุณุชุฎุฏูููุง ูู ุงููุทุจุฎ ุจูู ุณูููุฉ .\r\nโข ูุด ูุชูููู ูู ุงูุญุฑุงุฑุฉ ุงูุนุงููุฉ ููุง ุญุฑูุงู ูู ุงูุนูู .\r\nโข ูุชุดูู ุนูู ุงูุจูุชุฌุงุฒ ุจูู ุณูููุฉ ูู ุบูุฑ ูุญู ููุง ุญุฑุงุฑุฉูุด ูุชูุณู ุชุนูู ุฃูู ุงูุฏุงูุช ูุฃููุง ูุชุณูู ุนููู ู ู ุฎูุงู ุฏูุงูู ููููู ุฌุงูุฒ .ุจุชุดูู ุงูุฃูู ุจุทุฑููุฉ ุตุญูุฉ ุนู ุทุฑูู ุงูุญุฑุงุฑุฉ ู ุงูุจุฎุงุฑ .\r\nโข ูุชุณุงุนุฏู ุชุงูู ุฃูู ุตุญู ุฏุงููุง ุจุฏููู ุฃูู .\r\nโข ูุนุงูุง ุดุจูุฉ ุชุญุทู ุนูููุง ุงูุฃูู ู ุชุถููู ุงููุงูุฉ ูู ุงูุนูู ุงูุฏุงุฎูู ูููุง ู ุฎูุงู ุฏูุงูู ุงูุฃูู ูููู ุฌุงูุฒ .\r\nโข ุณููุฉ ุงูุฃุณุชุฎุฏุงู ู ูุชูุฏุฑู ุชูุถูููุง ุจุณูููุฉ .\r\nโข ุญุฌููุง ููุงุณุจ ุชูุฏุฑู ุชุนููู ูููุง ูุฑุฎุฉ ุฃู ูููู ูุญูุฉ\r\nโข ุงููุฏ ุจุชุงุนุชูุง ููุงููุฉ ููุญุฑุงุฑุฉ .\r\nโข *ุงููุตู*\r\nโข ูุตู ุทุจู ุณุญุฑู ูุงุฐุงุจุฉ ุงูุซูุฌ \r\nโข ุงูุงุจุนุงุฏ :- 21ร29 ุณู .\r\nโข ูุตู ุดูุงูุฉ  star max .\r\nโข ุงูุฃุจุนุงุฏ : 27.5 *22\r\nโข ููุงุณ ุงูุดุจูุฉ : 17*22\r\nโข ุงูุฎุงูุฉ :- ูุนุฏู .\r\nโข *ูุญุชูู ุงูุนุจูุฉ*\r\nโข 1รุทุจู ูุฅุฐุงุจุฉ ุงูุซูุฌ .\r\nโข 1รุดูุงูุฉ ุจูุชุฌุงุฒ .\r\nโข","media":["https://tager-uploads.s3.eu-central-1.amazonaws.com/386123b9-05d7-4468-b46b-80b82fbc3611.jpg","https://tager-uploads.s3.eu-central-1.amazonaws.com/ea3492f3-afb4-464a-b680-08d3ed9f1bc3.jpg","https://tager-uploads.s3.eu-central-1.amazonaws.com/2234fce4-45cf-44a4-919a-e6543e296c0d.jpg","https://tager-uploads.s3.eu-central-1.amazonaws.com/08e3f156-995b-4765-9f3a-c7377540a026.jpg","https://tager-uploads.s3.eu-central-1.amazonaws.com/c275d18b-6524-4c6a-8d8f-1d467a03805b.jpg"]},{"cat":{"name":"Taager exclusive offers","text":"ุนุฑูุถ ุชุงุฌุฑ ุงูุญุตุฑูุฉ"},"id":"EG030501KYMB99","status":"available","desc":"0","title":"ูุจุฉ ุงูุถุบุท ุงููุฏููุฉ ุงูุนุฌูุจุฉ + ูุถุฑุจ ุจูุถ ู ูุณูุงููู ูุฏูู ูุนูู ุจุงูุถุบุท","price":180,"specs":"โข 0","media":["https://tager-uploads.s3.eu-central-1.amazonaws.com/1511cb64-01b0-4162-9a32-41539edda024.jpg"]},{"cat":{"name":"Taager exclusive offers","text":"ุนุฑูุถ ุชุงุฌุฑ ุงูุญุตุฑูุฉ"},"id":"EG050701SP0099","status":"available","desc":"ูู ูุง ุชูุชู ุจุนุฑุจูุชู ุฃูุชุฑ ูู ูุง ุชุนูุด ูุนุงู ุฃุทูู๐ุ ูุนุดุงู  ูููู ูุถุงูุฉ ุนุฑุจูุชู ููุฑูุงูู ุนุฑุถ ุงูุฌููุฑ ูุชูุถูู ุงูุณูุงุฑุฉ ุนุฑุถ ูู ุงูุงุฎุฑุ ุงูุนุฑุจูุฉ ุจุชููุน ุจุฃูู ุชูุงููู ููุฌููุฏุ ุงุดุชุฑู ุงูุนุฑุถ ูุฏูุน ุนุฑุจูุชู.","title":"ุนุฑุถ ุงูุฌููุฑ ูุชูุถูู ุงูุณูุงุฑุฉ(ุณุจุฑุงู ุชุฌุฏูุฏ ุชุงุจููู ุงูุณูุงุฑุฉ + ููุธู ุงูุณูุงุฑุฉ ุงูุฌููุฑ+ูููุน ุงูุจูุงุณุชู ุงูุณุญุฑู P2+ ูุทุนุชูู ููุทุฉ ูุงููุฑู ูุงูุจุฑ ููุณูุงุฑุฉ)","price":250,"specs":"โข *ูููุฒุงุช ุณุจุฑุงู ุชุฌุฏูุฏ ุชุงุจููู ุงูุณูุงุฑุฉ*\r\nโข ููุญุงูุธ ุนูู ุงูุฌูุฏ ูู ุงูุชุฑุงุจ ูุงูุฃูุณุงุฎ\r\nโข ููุฎูู ุงูุฌูุฏ ุจูููุน ูุฃูู ุฌุฏูุฏุฉ\r\nโข ููุงุณุจ ุงุณุชุฎุฏุงูู ุงูุชุงุจููู ูุงููุฑุด ุงูุฏุงุฎูู\r\nโข ุณูู ุงูุงุณุชุฎุฏุงู ูุณุฑูุน ุงูููุนูู\r\nโข ุญุฌูู 150 ูู ูุชูุฏุฑ ุชุณุชุฎุฏูู ุงูุชุฑ ูู ูุฑู\r\nโข ููุงุณุจ ููู ุงููุงุน ุงูุณูุงุฑุช\r\nโข ุงููุตู\r\nโข ูููุน ุงูุฌูุฏ ููุณูุงุฑุฉ\r\nโข 150 ูู\r\nโข *ูููุฒุงุช ููุธู ุงูุณูุงุฑุฉ ุงูุฌููุฑ*\r\nโข 3 ูู 1 ููุธู ููููุน ููุนุทุฑ ุญุงูู ุงูุชุงุจููู\r\nโข ูุญุงูุธ ุนูู ุงูุชุงุจููู ูู ุงูุงุชุฑุจุฉ ู ุงูุงูุณุงุฎ\r\nโข ูุญุงูุธ ุนูู ููู ุงูุชุงุจููู ูู ุฃุดุนุฉ ุงูุดูุณ ู ุงูุชุดููุงุช\r\nโข ูุชููุฑ ุจุฑูุงุฆุญ ูุฎุชููุฉ ูุนุทุฑู ููุนุฑุจูุฉ (ูุฑุงููุฉุ ูุฑุฏุ ูู)\r\nโข ุชูุถูู ู ููุนุงู ููุฑุฌุน ุนุฑุจูุชู ุฌุฏูุฏุฉ ูู ุชุงูู\r\nโข ูุด ุจูุณูุจ ุทุจูุฉ ุฏูููุฉ ููุฏูู ููุนุฉ ุชุฏูู ููุช ุทููู\r\nโข ูุนุงู ุฃุณููุฌู ูุชูุถูู ูุงูุฃุณุชุฎุฏุงู ุจุณูููุฉ\r\nโข ุงููุตู\r\nโข ุงูุฎุงูุฉ: ุณูููููู\r\nโข ุงูุนุจูุฉ: 250 + 10% ููู\r\nโข ุงูุฑุงุฆุญุฉ: ุนุดูุงุฆู\r\nโข ูุญุชูู ุงูุนุจูุฉ\r\nโข ููุธู ุงูุณูุงุฑุฉ ุงูุฌููุฑ\r\nโข ุฃุณููุฌุฉ\r\nโข *ูููุฒุงุช ูููุน ุงูุจูุงุณุชู ุงูุณุญุฑู P2*\r\nโข ุงููููุน ุงูุณุญุฑู ููุฑุฌุนูู ููู ุงูุฃุณุทุญ ุงูุฌูุฏ ู ุงูุจูุงุณุชูู ุฒู ูุง ูุงูุช\r\nโข ูุชูุถู ุงูููุงู ุงููู ูุชููุนู ูู ุงูุฃุชุฑุจุฉ ุงูุฃูู ู ุจุนุฏูู ุชุณุชุฎุฏูู\r\nโข ูุชูุฏุฑ ุชุณุชุฎุฏูู ุนูู ุงูุฌูุฏ ู ุงูุจูุงุณุชูู\r\nโข 120 ููู ูููุนุฏ ูุนุงู ูุชุฑุฉ ุทูููุฉ\r\nโข ูุตู ุงูููุชุฌ\r\nโข ูููุน ุงูุจูุงุณุชู ุงูุณุญุฑู P2\r\nโข ุงูุณุนุฉ: 120 ููู\r\nโข ูุญุชูู ุงูุนุจูุฉ\r\nโข ูููุน ุงูุจูุงุณุชู ุงูุณุญุฑู P2\r\nโข *ูููุฒุงุช  ูุทุนุชูู ููุทุฉ ูุงููุฑู ูุงูุจุฑ ููุณูุงุฑุฉ*\r\nโข ูุด ูุชุญุชุงุฌ ุชุบุฑู ุงูุนุฑุจูุฉ ููู ูุงู ุงูููุทุฉ ุจุชูุถู ุชูุถูู ุฌุงู\r\nโข ูุชุฎูู ุนุฑุจูุชู ุจุชููุน\r\nโข ุชูุฏุฑ ุชููุน ุจููุง ูุฑุด ุงูุนุฑุจูุฉ ูุงูุชุงุจููู\r\nโข ุจุชูุชุต ุงูููุงู ุณุฑูุนุง\r\nโข ุฎุงูุชูุง ูููุฉ ุฌุฏุง ู ูุชุนูุด ูุนุงู ูุชุฑุฉ ุทูููุฉ\r\nโข ูุด ูุชุณุชุฎุฏู ูุนุงูุง ููุงุฏ ุชูุถูู\r\nโข ุงููุตู\r\nโข ุงูุฎุงูุฉ: ููุงุด ูููุฑูููุจุฑ\r\nโข ุนุฏุฏ: 2 ููุทุฉ (ูุจูุฑุฉุุตุบูุฑุฉ)\r\nโข ุงูุงุจุนุงุฏ(40*40)ู(40*30)\r\nโข","media":["https://tager-uploads.s3.eu-central-1.amazonaws.com/3efca926-3bfe-45f0-b2d5-3bc884ab054b.jpg","https://tager-uploads.s3.eu-central-1.amazonaws.com/ee828433-4793-4b50-819f-9b50eab7789e.jpg","https://tager-uploads.s3.eu-central-1.amazonaws.com/9c83dba5-20c7-4815-a694-efa1f219f674.jpg","https://tager-uploads.s3.eu-central-1.amazonaws.com/9baddbbe-87df-445d-8f4f-a94b31262023.png"]},{"cat":{"name":"Taager exclusive offers","text":"ุนุฑูุถ ุชุงุฌุฑ ุงูุญุตุฑูุฉ"},"id":"EG030501CUBU99","status":"available","desc":"ููุฑูุงูู ุฌู ุงูุณูููุง ูุญุฏ ุนูุฏู ูุน ุนุฑุถ ูุทุนุชูู ููุจุงูุฉ ุนุตูุฑ ู ูุดุงุฑ .","title":"ุนุฑุถ ูุทุนุชูู ููุจุงูุฉ ุนุตูุฑ ู ูุดุงุฑ 2 ูู 1","price":90,"specs":"โข *ุงููููุฒุงุช*\r\nโข ูุชูุฏุฑ ุชูุตู ุงูููุจุงูุฉ ุนู ุงูุทุจู ู ุชุณุชุฎุฏู ูู ูุงุญุฏ ููุญุฏู .\r\nโข ุงูุฎุงูุฉ ูู ุงูุจูุงุณุชูู ุงููููู ุตุนุจ ุงููุณุฑ .\r\nโข ูุชูุฏุฑ ุชุชุญุฑู ุจูู ูู ุงู ููุงู ูุงูู ุฎููู ู ูุด ุจูุงุฎุฏ ูุณุงุญุฉ ู ููุงู ุดูู .\r\nโข *ุงููุตู*\r\nโข ุงูุฎุงูุฉ :- ุจูุงุณุชูู .\r\nโข *ูุญุชูู ุงูุนุจูุฉ*\r\nโข 2รููุจุงูุฉ .\r\nโข","media":["https://tager-uploads.s3.eu-central-1.amazonaws.com/248ea927-83d6-45fd-83df-1bfe2c9122c2.jpg","https://tager-uploads.s3.eu-central-1.amazonaws.com/0f2c1f35-82de-46ae-8b18-0c479d5e0328.jpg","https://tager-uploads.s3.eu-central-1.amazonaws.com/211223ec-8acd-4559-9b14-c4ab61e532e6.jpg","https://tager-uploads.s3.eu-central-1.amazonaws.com/eda8e5dc-5629-45f9-a88a-5dd98d936f2e.jpg","https://tager-uploads.s3.eu-central-1.amazonaws.com/5f82791b-714a-46f2-9bc9-12e20e0be7de.jpg","https://tager-uploads.s3.eu-central-1.amazonaws.com/98de5dba-c770-4138-89aa-4bd9d29c5a19.jpg","https://tager-uploads.s3.eu-central-1.amazonaws.com/556b88d8-2297-4981-a576-c4b281f17a1d.jpg"]}]